Documents/CS - UTEC/ARQUITECTURA/Oyague_Macarena_L04/2/FSMBehavioral.v
module FSMBehavioral (input nreset, clk, x1, x2, x3,
                      output reg [2:0]y, z);

reg [2:0] next_state;

parameter a = 3'b000, b = 3'b001, c = 3'b101, d = 3'b010, e = 3'b100, f = 3'b110, g = 3'b111;

always @ (posedge clk)
begin
    if (~nreset)
        y = a;
    else
        y = next_state;
    case (y)
    d:
      z = 3'b100;
    e:
      z = 3'b010;
    g:
      z = 3'b001;
    default: 
      z = 3'b000;
    endcase
end

always @ (y or x1 or x2 or x3)
begin
    case (y)
    a:
        if (x1 == 1) next_state = b;
        else next_state = c;

    b: 
        if (x2 == 1) next_state = d;
        else next_state = a;
    c:
        if (x2 == 1 & x3 == 1) next_state = e;
        else if (x2 == 1 & x3 == 0) next_state = a;
        else if (x2 == 0 & x3 == 1) next_state = f;
        else if (x2 == 0 & x3 == 0) next_state = g;
    default: 
        next_state = a;
    endcase
end

endmodule

Documents/CS - UTEC/ARQUITECTURA/Oyague_Macarena_L04/2/FSMBehavioral_tb.v
module FSMBehavioral_tb;

    reg nreset, clk, x1, x2, x3;
    wire [2:0]y, z;

    FSMBehavioral fsm(.nreset(nreset), .clk(clk), .x1(x1), .x2(x2), 
                      .x3(x3), .y(y), .z(z));

    initial begin
        clk = 1;
        nreset = 0;
        {x1, x2, x3} = 3'b100; 
        #1 nreset = 1; 
        @(posedge clk) {x1, x2, x3} = 3'b010;
        @(posedge clk) {x1, x2, x3} = 3'b000; 
        @(posedge clk) {x1, x2, x3} = 3'b000; 
        @(posedge clk) {x1, x2, x3} = 3'b011;
        @(posedge clk) {x1, x2, x3} = 3'b011; 
        @(posedge clk) {x1, x2, x3} = 3'b001; 
        @(posedge clk) {x1, x2, x3} = 3'b000; 
        @(posedge clk) {x1, x2, x3} = 3'b000; 
        @(posedge clk) {x1, x2, x3} = 3'b000; 
        #14 $finish;
    end

    initial begin
        $monitor("%d ns:\tclk=%b\tnreset=%b\tx=%b%b%b\t y=%b\t z=%b", $time, clk, nreset, x1, x2, x3, y, z);
    end
    
    always #1 clk = !clk;

    initial begin
        $dumpfile("FSMBehavioral.vcd");
        $dumpvars;
    end
endmodule

Documents/CS - UTEC/ARQUITECTURA/Oyague_Macarena_L04/2/FSMBehavioral.vcd
$date
	Sun May 31 22:21:27 2020
$end
$version
	Icarus Verilog
$end
$timescale
	1s
$end
$scope module FSMBehavioral_tb $end
$var wire 3 ! z [2:0] $end
$var wire 3 " y [2:0] $end
$var reg 1 # clk $end
$var reg 1 $ nreset $end
$var reg 1 % x1 $end
$var reg 1 & x2 $end
$var reg 1 ' x3 $end
$scope module fsm $end
$var wire 1 # clk $end
$var wire 1 $ nreset $end
$var wire 1 % x1 $end
$var wire 1 & x2 $end
$var wire 1 ' x3 $end
$var reg 3 ( next_state [2:0] $end
$var reg 3 ) y [2:0] $end
$var reg 3 * z [2:0] $end
$upscope $end
$upscope $end
$enddefinitions $end
#0
$dumpvars
b0 *
b0 )
b1 (
0'
0&
1%
0$
1#
b0 "
b0 !
$end
#1
0#
1$
#2
b10 (
b1 "
b1 )
0%
1&
1#
#3
0#
#4
b0 (
0&
b100 !
b100 *
b10 "
b10 )
1#
#5
0#
#6
b101 (
b0 !
b0 *
b0 "
b0 )
1#
#7
0#
#8
b100 (
1&
1'
b101 "
b101 )
1#
#9
0#
#10
b0 (
b10 !
b10 *
b100 "
b100 )
1#
#11
0#
#12
b101 (
0&
b0 !
b0 *
b0 "
b0 )
1#
#13
0#
#14
b111 (
b101 "
b101 )
0'
1#
#15
0#
#16
b0 (
b1 !
b1 *
b111 "
b111 )
1#
#17
0#
#18
b101 (
b0 !
b0 *
b0 "
b0 )
1#
#19
0#
#20
b111 (
b101 "
b101 )
1#
#21
0#
#22
b0 (
b1 !
b1 *
b111 "
b111 )
1#
#23
0#
#24
b101 (
b0 !
b0 *
b0 "
b0 )
1#
#25
0#
#26
b111 (
b101 "
b101 )
1#
#27
0#
#28
b0 (
b1 !
b1 *
b111 "
b111 )
1#
#29
0#
#30
b101 (
b0 !
b0 *
b0 "
b0 )
1#
#31
0#
#32
b111 (
b101 "
b101 )
1#
