Documents/CS - UTEC/ARQUITECTURA/LAB 3 PRIMER INTENTO/Oyague_Macarena_L03/2/DFF_behavioral.v
module DFF_behavioral(   input d,
                         input clk,
                         input clrn,
                         output q);
    assign q = (clrn == 0 ? 0 : (clk == 0 ? q : (d == 0 ? 0 : 1)));
endmodule

Documents/CS - UTEC/ARQUITECTURA/LAB 3 PRIMER INTENTO/Oyague_Macarena_L03/2/DFF_behavioral_tb.v
`timescale 1ns/1ns
module DFF_tb;
    reg d, clk, clrn;
    wire q;
    DFF_behavioral dff(d, clk, clrn, q);
    initial begin
        clk = 1;
        d = 0;
        clrn = 1;
        $monitor("%d ns:\td=%h\tclk=%h\tclrn=%h\tq=%h", 
                 $time, d, clk, clrn, q);
        #20 $finish;
    end
    always #1 d =! d;
    always #2 clk =! clk;
    always #4 clrn =! clrn;
    initial begin
        $dumpfile("DFF_behavioral.vcd");
        $dumpvars;
    end
endmodule

Documents/CS - UTEC/ARQUITECTURA/LAB 3 PRIMER INTENTO/Oyague_Macarena_L03/2/DFF_behavioral.vcd
$date
	Thu May 14 23:13:55 2020
$end
$version
	Icarus Verilog
$end
$timescale
	1ns
$end
$scope module DFF_tb $end
$var wire 1 ! q $end
$var reg 1 " clk $end
$var reg 1 # clrn $end
$var reg 1 $ d $end
$scope module dff $end
$var wire 1 " clk $end
$var wire 1 # clrn $end
$var wire 1 $ d $end
$var wire 1 ! q $end
$upscope $end
$upscope $end
$enddefinitions $end
#0
$dumpvars
0$
1#
1"
0!
$end
#1
1!
1$
#2
0$
0"
#3
1$
#4
0!
0$
1"
0#
#5
1$
#6
0$
0"
#7
1$
#8
0!
0$
1"
1#
#9
1!
1$
#10
0$
0"
#11
1$
#12
0!
0$
1"
0#
#13
1$
#14
0$
0"
#15
1$
#16
0!
0$
1"
1#
#17
1!
1$
#18
0$
0"
#19
1$
#20
0!
0$
1"
0#
