Documents/CS - UTEC/ARQUITECTURA/LAB 3 PRIMER INTENTO/Oyague_Macarena_L03/2/DFF_behavioral.v
module DFF_behavioral(   input d,
                         input clk,
                         input clrn,
                         output q);
    assign q = (clrn == 0 ? 0 : (clk == 0 ? q : (d == 0 ? 0 : 1)));
endmodule

Documents/CS - UTEC/ARQUITECTURA/LAB 3 PRIMER INTENTO/Oyague_Macarena_L03/2/mux_2_1.v
module mux2_1(  input input1,
                input input2,
                input selector,
                output output1);
  assign output1 = selector ? input2 : input1;
endmodule

Documents/CS - UTEC/ARQUITECTURA/LAB 3 PRIMER INTENTO/Oyague_Macarena_L03/2/SchematicMisterioso.v
`include "mux_2_1.v"
`include "DFF_behavioral.v"
module SchematicMisterioso(   input [2:0]d,
                              input di,
                              input load,
                              input clk,
                              input clrn,
                              output [2:0]q,
                              output do);
    wire out_mux1, out_mux2, out_mux3;
    mux2_1 mux1(di, d[2], load, out_mux1);
    DFF_behavioral dff1(out_mux1, clk, clrn, q[2]);
    mux2_1 mux2(q[2], d[1], load, out_mux2);
    DFF_behavioral dff2(out_mux2, clk, clrn, q[1]);
    mux2_1 mux3(q[1], d[0], load, out_mux3);
    DFF_behavioral dff3(out_mux3, clk, clrn, q[0]);
    assign do = q[0];
endmodule

Documents/CS - UTEC/ARQUITECTURA/LAB 3 PRIMER INTENTO/Oyague_Macarena_L03/2/SchematicMisterioso_tb.v
`timescale 1ns/1ns
module SchematicMisterioso_tb;
    reg [2:0]d;
    reg di, load, clk, clrn;
    wire [2:0]q;
    wire do;
    SchematicMisterioso SM(d, di, load, clk, clrn, q, do);
    initial begin
        clk = 1;
        di = 0;
        d = 3'b000;
        clrn = 1;
        load = 1;
        $monitor("%d ns:\td=%b  di=%b  load=%b  clk=%b  clrn=%b  q=%b  do=%b", 
                 $time, d, di, load, clk, clrn, q, do);
        #20 $finish;
    end
    always #1 di =! di;
    always #1 d = $random;
    always #3 clk =! clk;
    always #4 load =! load;
    always #12 clrn =! clrn;
    initial begin
        $dumpfile("SM.vcd");
        $dumpvars;
    end
endmodule

Documents/CS - UTEC/ARQUITECTURA/LAB 3 PRIMER INTENTO/Oyague_Macarena_L03/2/SM.vcd
$date
	Sat May 16 16:28:14 2020
$end
$version
	Icarus Verilog
$end
$timescale
	1ns
$end
$scope module SchematicMisterioso_tb $end
$var wire 3 ! q [2:0] $end
$var wire 1 " do $end
$var reg 1 # clk $end
$var reg 1 $ clrn $end
$var reg 3 % d [2:0] $end
$var reg 1 & di $end
$var reg 1 ' load $end
$scope module SM $end
$var wire 1 # clk $end
$var wire 1 $ clrn $end
$var wire 3 ( d [2:0] $end
$var wire 1 & di $end
$var wire 1 ' load $end
$var wire 3 ) q [2:0] $end
$var wire 1 * out_mux3 $end
$var wire 1 + out_mux2 $end
$var wire 1 , out_mux1 $end
$var wire 1 " do $end
$scope module dff1 $end
$var wire 1 # clk $end
$var wire 1 $ clrn $end
$var wire 1 - q $end
$var wire 1 , d $end
$upscope $end
$scope module dff2 $end
$var wire 1 # clk $end
$var wire 1 $ clrn $end
$var wire 1 . q $end
$var wire 1 + d $end
$upscope $end
$scope module dff3 $end
$var wire 1 # clk $end
$var wire 1 $ clrn $end
$var wire 1 / q $end
$var wire 1 * d $end
$upscope $end
$scope module mux1 $end
$var wire 1 & input1 $end
$var wire 1 0 input2 $end
$var wire 1 ' selector $end
$var wire 1 , output1 $end
$upscope $end
$scope module mux2 $end
$var wire 1 1 input1 $end
$var wire 1 2 input2 $end
$var wire 1 ' selector $end
$var wire 1 + output1 $end
$upscope $end
$scope module mux3 $end
$var wire 1 3 input1 $end
$var wire 1 4 input2 $end
$var wire 1 ' selector $end
$var wire 1 * output1 $end
$upscope $end
$upscope $end
$upscope $end
$enddefinitions $end
#0
$dumpvars
04
03
02
01
00
0/
0.
0-
0,
0+
0*
b0 )
b0 (
1'
0&
b0 %
1$
1#
0"
b0 !
$end
#1
11
b100 !
b100 )
1-
1,
10
b100 %
b100 (
1&
#2
01
1"
0-
b1 !
b1 )
1/
0,
1*
00
14
b1 %
b1 (
0&
#3
1&
0#
#4
12
0*
b11 %
b11 (
0&
0'
#5
10
02
1,
b101 %
b101 (
1&
#6
0*
03
0.
0+
01
0"
0-
b0 !
b0 )
0/
0,
0&
1#
#7
1"
1/
1*
13
1.
1+
11
b111 !
b111 )
1-
1,
1&
#8
01
0"
0-
0/
13
b10 !
b10 )
1.
0,
0*
00
12
04
1+
b10 %
b10 (
0&
1'
#9
0+
1*
02
14
b1 %
b1 (
1&
0#
#10
1,
10
b101 %
b101 (
0&
#11
1+
0*
12
04
b110 %
b110 (
1&
#12
03
b0 !
b0 )
0.
02
14
0,
0+
0*
b101 %
b101 (
0&
1#
0'
0$
#13
1,
1&
#14
04
0,
b100 %
b100 (
0&
#15
00
14
1,
b1 %
b1 (
1&
0#
#16
1+
10
12
04
1,
0*
b110 %
b110 (
0&
1'
#17
0+
1*
02
14
b101 %
b101 (
1&
#18
0,
1+
0*
00
12
04
b10 %
b10 (
0&
1#
#19
1,
0+
1*
10
02
14
b101 %
b101 (
1&
#20
0,
0*
0&
0'
