Documents/CS - UTEC/ARQUITECTURA/Oyague_Macarena_L02/5/encoder_8_3.v
module encoder8_3 (   input [7:0]input1,
                      input enable,
                      output reg [2:0]output1,
                      output reg g);
    always @(input1) begin
      casex(input1)
            8'b00000000 : output1 =  enable == 1 ? 3'b000 : 0;
            8'b00000001 : output1 =  enable == 1 ? 3'b000 : 0;
            8'b0000001X : output1 =  enable == 1 ? 3'b001 : 0;
            8'b000001XX : output1 =  enable == 1 ? 3'b010 : 0;
            8'b00001XXX : output1 =  enable == 1 ? 3'b011 : 0;
            8'b0001XXXX : output1 =  enable == 1 ? 3'b100 : 0;
            8'b001XXXXX : output1 =  enable == 1 ? 3'b101 : 0;
            8'b01XXXXXX : output1 =  enable == 1 ? 3'b110 : 0;
            8'b1XXXXXXX : output1 =  enable == 1 ? 3'b111 : 0;
      endcase
    end
    always @(input1) begin
      if (output1 == 3'b000 && input1 == 8'b00000000) begin
        g = 0;
      end else if (enable == 0) begin
        g = 0;
      end else begin
        g = 1;
      end
    end
endmodule

Documents/CS - UTEC/ARQUITECTURA/Oyague_Macarena_L02/5/encoder_8_3_tb.v
`timescale 1ns/1ns
module encoder8_3_tb;
    reg [7:0]input1;
    reg enable;
    wire [2:0]output1;
    wire g;
    encoder8_3 encoder(input1, enable, output1, g);
    initial begin
        input1[0] = 0;
        input1[1] = 0;
        input1[2] = 0;
        input1[3] = 0;
        input1[4] = 0;
        input1[5] = 0;
        input1[6] = 0;
        input1[7] = 0;
        enable = 1;
        $monitor("%d ns:   enable=%b    in[0]=%b in[1]=%b in[2]=%b in[3]=%h in[4]=%h in[5]=%h in[6]=%h in[7]=%h     out[0]=%h out[1]=%h out[2]=%h   g=%b", 
                $time, enable, input1[0], input1[1], input1[2], input1[3], input1[4], input1[5], input1[6], input1[7], output1[0], output1[1], output1[2], g);
        #10 $finish;
    end
    always #1 input1[0]=!input1[0];
    always #2 input1[1]=!input1[1];
    always #3 input1[2]=!input1[2];
    always #4 input1[3]=!input1[3];
    always #5 input1[4]=!input1[4];
    always #6 input1[5]=!input1[5];
    always #7 input1[6]=!input1[6];
    always #8 input1[7]=!input1[7];
    always #9 enable=!enable;
    initial begin
        $dumpfile("encoder_8_3.vcd");
        $dumpvars;
    end
endmodule

Documents/CS - UTEC/ARQUITECTURA/Oyague_Macarena_L02/5/encoder_8_3.vcd
$date
	Thu May  7 20:27:36 2020
$end
$version
	Icarus Verilog
$end
$timescale
	1ns
$end
$scope module encoder8_3_tb $end
$var wire 3 ! output1 [2:0] $end
$var wire 1 " g $end
$var reg 1 # enable $end
$var reg 8 $ input1 [7:0] $end
$scope module encoder $end
$var wire 1 # enable $end
$var wire 8 % input1 [7:0] $end
$var reg 1 " g $end
$var reg 3 & output1 [2:0] $end
$upscope $end
$upscope $end
$enddefinitions $end
#0
$dumpvars
b0 &
b0 %
b0 $
1#
0"
b0 !
$end
#1
1"
b1 $
b1 %
#2
b1 !
b1 &
b10 $
b10 %
#3
b10 !
b10 &
b111 $
b111 %
#4
b11 !
b11 &
b1100 $
b1100 %
#5
b100 !
b100 &
b11101 $
b11101 %
#6
b101 !
b101 &
b111010 $
b111010 %
#7
b110 !
b110 &
b1111011 $
b1111011 %
#8
b111 !
b111 &
b11110000 $
b11110000 %
#9
b0 !
b0 &
0"
b11110101 $
b11110101 %
0#
#10
b11100110 $
b11100110 %
