Documents/CS - UTEC/ARQUITECTURA/Ostolaza_Oyague_L05/alu.v
module mux2_1 (logicU, arithU, sel, out);
    input [31:0] logicU, arithU;
    input sel;
    output [31:0] out;
    assign out = sel ? logicU : arithU;
endmodule

module alu (A, B, opcode, result, zero);
    input[31:0] A, B;
    input [3:0] opcode;
    output [31:0] result;
    output zero;
    wire [31:0] outLogic, outArithmetic;

    logicUnit log(A, B, opcode, outLogic);
    arithmetic ari(A, B, opcode, outArithmetic);
    mux2_1 mux(outLogic, outArithmetic, opcode[2], result);
    assign zero = (result == 31'b0) ? 1 : 0;
endmodule

Documents/CS - UTEC/ARQUITECTURA/semana11/arithmetic.v
module arithmetic (A, B, opcode, out);
    input[31:0] A, B;
    input [3:0] opcode;
    output [31:0] out;
    reg [31:0] out;

    parameter add = 4'b0000, sub = 4'b0010, slt = 4'b1010;

    always @ (A or B or opcode) begin
        casex (opcode)
            add: out = A + B;
            sub: out = A - B;
            slt: out = (A < B) ? 1 : 0;
            default: out = 31'b0;
        endcase
    end

endmodule

Documents/CS - UTEC/ARQUITECTURA/semana11/logic.v
module logicUnit (A, B, opcode, out);
    input[31:0] A, B;
    input [3:0] opcode;
    output [31:0] out;
    reg [31:0] out;

    parameter and_ = 4'b0100, or_ = 4'b0101, xor_ = 4'b0110, nor_ = 4'b0111;

    always @ (A or B or opcode) begin
        casex (opcode)
            and_: out = A & B;
            or_: out = A | B;
            xor_: out = A ^ B;
            nor_: out = ~(A | B);
            default: out = 31'b0;
        endcase
    end

endmodule

Documents/CS - UTEC/ARQUITECTURA/Ostolaza_Oyague_L05/alu_tb.v
module alu_tb;

reg[31:0] A, B; 
reg[3:0] opcode;
wire[31:0] result; 

initial 
$monitor ("A = %b, B =%b, opcode = %b, Result = %b, Zero = %b", A, B, opcode, result, zero);

initial
begin
    A = 15;
    B = 10;

    #1 opcode = 4'b0000;
    #1 opcode = 4'b0010;
    #1 opcode = 4'b0100;
    #1 opcode = 4'b0101;
    #1 opcode = 4'b0110;
    #1 opcode = 4'b0111;
    #1 opcode = 4'b1010;
    #1 opcode = 4'bx;

	#8 $finish;

end

alu inst1 (A, B, opcode, result, zero);

initial begin
        $dumpfile("alu.vcd");
        $dumpvars;
end

endmodule

Documents/CS - UTEC/ARQUITECTURA/Ostolaza_Oyague_L05/alu.vcd
$date
	Sun Jun 14 19:15:07 2020
$end
$version
	Icarus Verilog
$end
$timescale
	1s
$end
$scope module alu_tb $end
$var wire 1 ! zero $end
$var wire 32 " result [31:0] $end
$var reg 32 # A [31:0] $end
$var reg 32 $ B [31:0] $end
$var reg 4 % opcode [3:0] $end
$scope module inst1 $end
$var wire 32 & A [31:0] $end
$var wire 32 ' B [31:0] $end
$var wire 4 ( opcode [3:0] $end
$var wire 1 ! zero $end
$var wire 32 ) result [31:0] $end
$var wire 32 * outLogic [31:0] $end
$var wire 32 + outArithmetic [31:0] $end
$scope module ari $end
$var wire 32 , A [31:0] $end
$var wire 32 - B [31:0] $end
$var wire 4 . opcode [3:0] $end
$var reg 32 / out [31:0] $end
$upscope $end
$scope module log $end
$var wire 32 0 A [31:0] $end
$var wire 32 1 B [31:0] $end
$var wire 4 2 opcode [3:0] $end
$var reg 32 3 out [31:0] $end
$upscope $end
$scope module mux $end
$var wire 32 4 arithU [31:0] $end
$var wire 32 5 logicU [31:0] $end
$var wire 1 6 sel $end
$var wire 32 7 out [31:0] $end
$upscope $end
$upscope $end
$upscope $end
$enddefinitions $end
#0
$dumpvars
b0x10xx 7
x6
b1010 5
b11001 4
b1010 3
bx 2
b1010 1
b1111 0
b11001 /
bx .
b1010 -
b1111 ,
b11001 +
b1010 *
b0x10xx )
bx (
b1010 '
b1111 &
bx %
b1010 $
b1111 #
b0x10xx "
0!
$end
#1
b11001 "
b11001 )
b11001 7
06
b0 *
b0 3
b0 5
b0 %
b0 (
b0 .
b0 2
#2
b101 "
b101 )
b101 7
b101 +
b101 /
b101 4
b10 %
b10 (
b10 .
b10 2
#3
b1010 "
b1010 )
b1010 7
16
b1010 *
b1010 3
b1010 5
b0 +
b0 /
b0 4
b100 %
b100 (
b100 .
b100 2
#4
b1111 "
b1111 )
b1111 7
b1111 *
b1111 3
b1111 5
b101 %
b101 (
b101 .
b101 2
#5
b101 "
b101 )
b101 7
b101 *
b101 3
b101 5
b110 %
b110 (
b110 .
b110 2
#6
b11111111111111111111111111110000 "
b11111111111111111111111111110000 )
b11111111111111111111111111110000 7
b11111111111111111111111111110000 *
b11111111111111111111111111110000 3
b11111111111111111111111111110000 5
b111 %
b111 (
b111 .
b111 2
#7
1!
b0 "
b0 )
b0 7
06
b0 *
b0 3
b0 5
b1010 %
b1010 (
b1010 .
b1010 2
#8
0!
b0x10xx "
b0x10xx )
b0x10xx 7
x6
b11001 +
b11001 /
b11001 4
b1010 *
b1010 3
b1010 5
bx %
bx (
bx .
bx 2
