Documents/CS - UTEC/ARQUITECTURA/Oyague_Macarena_L02/3/demux_1_2.v
module demux1_2(  input [15:0]input1,
                   input selector,
                   output [15:0]output1,
                   output [15:0]output2);
    assign output1 = selector ? 0 : input1;
    assign output2 = selector ? input1 : 0;
endmodule

Documents/CS - UTEC/ARQUITECTURA/Oyague_Macarena_L02/3/demux_1_4.v
`include "demux_1_2.v"
module demux1_4 (  input [15:0]input1,
                   input [1:0]selector,
                   output [15:0]output1,
                   output [15:0]output2,
                   output [15:0]output3,
                   output [15:0]output4);
    wire [15:0]submodule1_a, submodule1_b, submodule2_a, submodule2_b;
    demux1_2 mux1(input1, selector[0], submodule1_a, submodule1_b);
    demux1_2 mux2(input1, selector[0], submodule2_a, submodule2_b);
    assign output1 = selector[1] ? 0 : submodule1_a;
    assign output2 = selector[1] ? 0 : submodule1_b;
    assign output3 = selector[1] ? submodule2_a : 0;
    assign output4 = selector[1] ? submodule2_b : 0;
endmodule

Documents/CS - UTEC/ARQUITECTURA/Oyague_Macarena_L02/3/demux_1_8.v
`include "demux_1_4.v"
module demux1_8 (  input [15:0]input1,
                   input [2:0]selector,
                   output [15:0]output1,
                   output [15:0]output2,
                   output [15:0]output3,
                   output [15:0]output4,
                   output [15:0]output5,
                   output [15:0]output6,
                   output [15:0]output7,
                   output [15:0]output8);
    wire [15:0]submodule1_a, submodule1_b, submodule1_c, submodule1_d, submodule2_a, submodule2_b, submodule2_c, submodule2_d;
    demux1_4 mux1(input1, selector[1:0], submodule1_a, submodule1_b, submodule1_c, submodule1_d);
    demux1_4 mux2(input1, selector[1:0], submodule2_a, submodule2_b, submodule2_c, submodule2_d);
    assign output1 = selector[2] ? 0 : submodule1_a;
    assign output2 = selector[2] ? 0 : submodule1_b;
    assign output3 = selector[2] ? 0 : submodule1_c;
    assign output4 = selector[2] ? 0 : submodule1_d;
    assign output5 = selector[2] ? submodule2_a : 0;
    assign output6 = selector[2] ? submodule2_b : 0;
    assign output7 = selector[2] ? submodule2_c : 0;
    assign output8 = selector[2] ? submodule2_d : 0;
endmodule

Documents/CS - UTEC/ARQUITECTURA/Oyague_Macarena_L02/3/demux_1_16.v
`include "demux_1_8.v"
module demux1_16(  input [15:0]input1,
                   input [3:0]selector,
                   output [15:0]output1,
                   output [15:0]output2,
                   output [15:0]output3,
                   output [15:0]output4,
                   output [15:0]output5,
                   output [15:0]output6,
                   output [15:0]output7,
                   output [15:0]output8,
                   output [15:0]output9,
                   output [15:0]output10,
                   output [15:0]output11,
                   output [15:0]output12,
                   output [15:0]output13,
                   output [15:0]output14,
                   output [15:0]output15,
                   output [15:0]output16);
    wire [15:0]submodule1_a, submodule1_b, submodule1_c, submodule1_d, submodule1_e, submodule1_f, submodule1_g, submodule1_h;
    wire [15:0]submodule2_a, submodule2_b, submodule2_c, submodule2_d, submodule2_e, submodule2_f, submodule2_g, submodule2_h;
    demux1_8 mux1(input1, selector[2:0], submodule1_a, submodule1_b, submodule1_c, submodule1_d, submodule1_e, submodule1_f, submodule1_g, submodule1_h);
    demux1_8 mux2(input1, selector[2:0], submodule2_a, submodule2_b, submodule2_c, submodule2_d, submodule2_e, submodule2_f, submodule2_g, submodule2_h);
    assign output1 = selector[3] ? 0 : submodule1_a;
    assign output2 = selector[3] ? 0 : submodule1_b;
    assign output3 = selector[3] ? 0 : submodule1_c;
    assign output4 = selector[3] ? 0 : submodule1_d;
    assign output5 = selector[3] ? 0 : submodule1_e;
    assign output6 = selector[3] ? 0 : submodule1_f;
    assign output7 = selector[3] ? 0 : submodule1_g;
    assign output8 = selector[3] ? 0 : submodule1_h;
    assign output9 = selector[3] ? submodule2_a : 0;
    assign output10 = selector[3] ? submodule2_b : 0;
    assign output11 = selector[3] ? submodule2_c : 0;
    assign output12 = selector[3] ? submodule2_d : 0;
    assign output13 = selector[3] ? submodule2_e : 0;
    assign output14 = selector[3] ? submodule2_f : 0;
    assign output15 = selector[3] ? submodule2_g : 0;
    assign output16 = selector[3] ? submodule2_h : 0;
endmodule

Documents/CS - UTEC/ARQUITECTURA/Oyague_Macarena_L02/3/demux_1_16_tb.v
`timescale 1ns/1ns
module demux1_16_tb;
    reg [15:0]input1;
    reg [3:0]selector;
    wire [15:0]output1, output2, output3, output4, output5, output6, output7, output8, output9, output10, output11, output12, output13, output14, output15, output16;
    demux1_16 mux(input1, selector, output1, output2, output3, output4, output5, output6, output7, output8, output9, output10, output11, output12, output13, output14, output15, output16);
    initial begin
        selector[0] = 0;
        selector[1] = 0;
        selector[2] = 0;
        selector[3] = 0;
        input1=$random;
        $monitor("%d ns:   sel[0]=%b sel[1]=%b sel[2]=%b in1=%h   out1=%h out2=%h out3=%h out4=%h out5=%h out6=%h out7=%h out8=%h out9=%h out10=%h out11=%h out12=%h out13=%h out14=%h out15=%h out16=%h", 
                $time, selector[0], selector[1], selector[2], input1, output1, output2, output3, output4, output5, output6, output7, output8, output9, output10, output11, output12, output13, output14, output15, output16);
        #16 $finish;
    end
    always #1 selector[0]=!selector[0];
    always #2 selector[1]=!selector[1];
    always #4 selector[2]=!selector[2];
    always #8 selector[3]=!selector[3];
    initial begin
        $dumpfile("demux1_16.vcd");
        $dumpvars;
    end
endmodule

Documents/CS - UTEC/ARQUITECTURA/Oyague_Macarena_L02/3/demux1_16.vcd
$date
	Thu May  7 20:24:34 2020
$end
$version
	Icarus Verilog
$end
$timescale
	1ns
$end
$scope module demux1_16_tb $end
$var wire 16 ! output9 [15:0] $end
$var wire 16 " output8 [15:0] $end
$var wire 16 # output7 [15:0] $end
$var wire 16 $ output6 [15:0] $end
$var wire 16 % output5 [15:0] $end
$var wire 16 & output4 [15:0] $end
$var wire 16 ' output3 [15:0] $end
$var wire 16 ( output2 [15:0] $end
$var wire 16 ) output16 [15:0] $end
$var wire 16 * output15 [15:0] $end
$var wire 16 + output14 [15:0] $end
$var wire 16 , output13 [15:0] $end
$var wire 16 - output12 [15:0] $end
$var wire 16 . output11 [15:0] $end
$var wire 16 / output10 [15:0] $end
$var wire 16 0 output1 [15:0] $end
$var reg 16 1 input1 [15:0] $end
$var reg 4 2 selector [3:0] $end
$scope module mux $end
$var wire 16 3 input1 [15:0] $end
$var wire 4 4 selector [3:0] $end
$var wire 16 5 submodule2_h [15:0] $end
$var wire 16 6 submodule2_g [15:0] $end
$var wire 16 7 submodule2_f [15:0] $end
$var wire 16 8 submodule2_e [15:0] $end
$var wire 16 9 submodule2_d [15:0] $end
$var wire 16 : submodule2_c [15:0] $end
$var wire 16 ; submodule2_b [15:0] $end
$var wire 16 < submodule2_a [15:0] $end
$var wire 16 = submodule1_h [15:0] $end
$var wire 16 > submodule1_g [15:0] $end
$var wire 16 ? submodule1_f [15:0] $end
$var wire 16 @ submodule1_e [15:0] $end
$var wire 16 A submodule1_d [15:0] $end
$var wire 16 B submodule1_c [15:0] $end
$var wire 16 C submodule1_b [15:0] $end
$var wire 16 D submodule1_a [15:0] $end
$var wire 16 E output9 [15:0] $end
$var wire 16 F output8 [15:0] $end
$var wire 16 G output7 [15:0] $end
$var wire 16 H output6 [15:0] $end
$var wire 16 I output5 [15:0] $end
$var wire 16 J output4 [15:0] $end
$var wire 16 K output3 [15:0] $end
$var wire 16 L output2 [15:0] $end
$var wire 16 M output16 [15:0] $end
$var wire 16 N output15 [15:0] $end
$var wire 16 O output14 [15:0] $end
$var wire 16 P output13 [15:0] $end
$var wire 16 Q output12 [15:0] $end
$var wire 16 R output11 [15:0] $end
$var wire 16 S output10 [15:0] $end
$var wire 16 T output1 [15:0] $end
$scope module mux1 $end
$var wire 16 U input1 [15:0] $end
$var wire 3 V selector [2:0] $end
$var wire 16 W submodule2_d [15:0] $end
$var wire 16 X submodule2_c [15:0] $end
$var wire 16 Y submodule2_b [15:0] $end
$var wire 16 Z submodule2_a [15:0] $end
$var wire 16 [ submodule1_d [15:0] $end
$var wire 16 \ submodule1_c [15:0] $end
$var wire 16 ] submodule1_b [15:0] $end
$var wire 16 ^ submodule1_a [15:0] $end
$var wire 16 _ output8 [15:0] $end
$var wire 16 ` output7 [15:0] $end
$var wire 16 a output6 [15:0] $end
$var wire 16 b output5 [15:0] $end
$var wire 16 c output4 [15:0] $end
$var wire 16 d output3 [15:0] $end
$var wire 16 e output2 [15:0] $end
$var wire 16 f output1 [15:0] $end
$scope module mux1 $end
$var wire 16 g input1 [15:0] $end
$var wire 2 h selector [1:0] $end
$var wire 16 i submodule2_b [15:0] $end
$var wire 16 j submodule2_a [15:0] $end
$var wire 16 k submodule1_b [15:0] $end
$var wire 16 l submodule1_a [15:0] $end
$var wire 16 m output4 [15:0] $end
$var wire 16 n output3 [15:0] $end
$var wire 16 o output2 [15:0] $end
$var wire 16 p output1 [15:0] $end
$scope module mux1 $end
$var wire 16 q input1 [15:0] $end
$var wire 1 r selector $end
$var wire 16 s output2 [15:0] $end
$var wire 16 t output1 [15:0] $end
$upscope $end
$scope module mux2 $end
$var wire 16 u input1 [15:0] $end
$var wire 1 v selector $end
$var wire 16 w output2 [15:0] $end
$var wire 16 x output1 [15:0] $end
$upscope $end
$upscope $end
$scope module mux2 $end
$var wire 16 y input1 [15:0] $end
$var wire 2 z selector [1:0] $end
$var wire 16 { submodule2_b [15:0] $end
$var wire 16 | submodule2_a [15:0] $end
$var wire 16 } submodule1_b [15:0] $end
$var wire 16 ~ submodule1_a [15:0] $end
$var wire 16 !" output4 [15:0] $end
$var wire 16 "" output3 [15:0] $end
$var wire 16 #" output2 [15:0] $end
$var wire 16 $" output1 [15:0] $end
$scope module mux1 $end
$var wire 16 %" input1 [15:0] $end
$var wire 1 &" selector $end
$var wire 16 '" output2 [15:0] $end
$var wire 16 (" output1 [15:0] $end
$upscope $end
$scope module mux2 $end
$var wire 16 )" input1 [15:0] $end
$var wire 1 *" selector $end
$var wire 16 +" output2 [15:0] $end
$var wire 16 ," output1 [15:0] $end
$upscope $end
$upscope $end
$upscope $end
$scope module mux2 $end
$var wire 16 -" input1 [15:0] $end
$var wire 3 ." selector [2:0] $end
$var wire 16 /" submodule2_d [15:0] $end
$var wire 16 0" submodule2_c [15:0] $end
$var wire 16 1" submodule2_b [15:0] $end
$var wire 16 2" submodule2_a [15:0] $end
$var wire 16 3" submodule1_d [15:0] $end
$var wire 16 4" submodule1_c [15:0] $end
$var wire 16 5" submodule1_b [15:0] $end
$var wire 16 6" submodule1_a [15:0] $end
$var wire 16 7" output8 [15:0] $end
$var wire 16 8" output7 [15:0] $end
$var wire 16 9" output6 [15:0] $end
$var wire 16 :" output5 [15:0] $end
$var wire 16 ;" output4 [15:0] $end
$var wire 16 <" output3 [15:0] $end
$var wire 16 =" output2 [15:0] $end
$var wire 16 >" output1 [15:0] $end
$scope module mux1 $end
$var wire 16 ?" input1 [15:0] $end
$var wire 2 @" selector [1:0] $end
$var wire 16 A" submodule2_b [15:0] $end
$var wire 16 B" submodule2_a [15:0] $end
$var wire 16 C" submodule1_b [15:0] $end
$var wire 16 D" submodule1_a [15:0] $end
$var wire 16 E" output4 [15:0] $end
$var wire 16 F" output3 [15:0] $end
$var wire 16 G" output2 [15:0] $end
$var wire 16 H" output1 [15:0] $end
$scope module mux1 $end
$var wire 16 I" input1 [15:0] $end
$var wire 1 J" selector $end
$var wire 16 K" output2 [15:0] $end
$var wire 16 L" output1 [15:0] $end
$upscope $end
$scope module mux2 $end
$var wire 16 M" input1 [15:0] $end
$var wire 1 N" selector $end
$var wire 16 O" output2 [15:0] $end
$var wire 16 P" output1 [15:0] $end
$upscope $end
$upscope $end
$scope module mux2 $end
$var wire 16 Q" input1 [15:0] $end
$var wire 2 R" selector [1:0] $end
$var wire 16 S" submodule2_b [15:0] $end
$var wire 16 T" submodule2_a [15:0] $end
$var wire 16 U" submodule1_b [15:0] $end
$var wire 16 V" submodule1_a [15:0] $end
$var wire 16 W" output4 [15:0] $end
$var wire 16 X" output3 [15:0] $end
$var wire 16 Y" output2 [15:0] $end
$var wire 16 Z" output1 [15:0] $end
$scope module mux1 $end
$var wire 16 [" input1 [15:0] $end
$var wire 1 \" selector $end
$var wire 16 ]" output2 [15:0] $end
$var wire 16 ^" output1 [15:0] $end
$upscope $end
$scope module mux2 $end
$var wire 16 _" input1 [15:0] $end
$var wire 1 `" selector $end
$var wire 16 a" output2 [15:0] $end
$var wire 16 b" output1 [15:0] $end
$upscope $end
$upscope $end
$upscope $end
$upscope $end
$upscope $end
$enddefinitions $end
#0
$dumpvars
b11010100100100 b"
b0 a"
0`"
b11010100100100 _"
b11010100100100 ^"
b0 ]"
0\"
b11010100100100 ["
b11010100100100 Z"
b0 Y"
b0 X"
b0 W"
b11010100100100 V"
b0 U"
b11010100100100 T"
b0 S"
b0 R"
b11010100100100 Q"
b11010100100100 P"
b0 O"
0N"
b11010100100100 M"
b11010100100100 L"
b0 K"
0J"
b11010100100100 I"
b11010100100100 H"
b0 G"
b0 F"
b0 E"
b11010100100100 D"
b0 C"
b11010100100100 B"
b0 A"
b0 @"
b11010100100100 ?"
b11010100100100 >"
b0 ="
b0 <"
b0 ;"
b0 :"
b0 9"
b0 8"
b0 7"
b11010100100100 6"
b0 5"
b0 4"
b0 3"
b11010100100100 2"
b0 1"
b0 0"
b0 /"
b0 ."
b11010100100100 -"
b11010100100100 ,"
b0 +"
0*"
b11010100100100 )"
b11010100100100 ("
b0 '"
0&"
b11010100100100 %"
b11010100100100 $"
b0 #"
b0 ""
b0 !"
b11010100100100 ~
b0 }
b11010100100100 |
b0 {
b0 z
b11010100100100 y
b11010100100100 x
b0 w
0v
b11010100100100 u
b11010100100100 t
b0 s
0r
b11010100100100 q
b11010100100100 p
b0 o
b0 n
b0 m
b11010100100100 l
b0 k
b11010100100100 j
b0 i
b0 h
b11010100100100 g
b11010100100100 f
b0 e
b0 d
b0 c
b0 b
b0 a
b0 `
b0 _
b11010100100100 ^
b0 ]
b0 \
b0 [
b11010100100100 Z
b0 Y
b0 X
b0 W
b0 V
b11010100100100 U
b11010100100100 T
b0 S
b0 R
b0 Q
b0 P
b0 O
b0 N
b0 M
b0 L
b0 K
b0 J
b0 I
b0 H
b0 G
b0 F
b0 E
b11010100100100 D
b0 C
b0 B
b0 A
b0 @
b0 ?
b0 >
b0 =
b11010100100100 <
b0 ;
b0 :
b0 9
b0 8
b0 7
b0 6
b0 5
b0 4
b11010100100100 3
b0 2
b11010100100100 1
b11010100100100 0
b0 /
b0 .
b0 -
b0 ,
b0 +
b0 *
b0 )
b0 (
b0 '
b0 &
b0 %
b0 $
b0 #
b0 "
b0 !
$end
#1
b0 0
b0 T
b11010100100100 (
b11010100100100 L
b0 D
b0 f
b11010100100100 C
b11010100100100 e
b0 <
b0 >"
b11010100100100 ;
b11010100100100 ="
b0 ^
b0 p
b11010100100100 ]
b11010100100100 o
b0 Z
b0 $"
b11010100100100 Y
b11010100100100 #"
b0 6"
b0 H"
b11010100100100 5"
b11010100100100 G"
b0 2"
b0 Z"
b11010100100100 1"
b11010100100100 Y"
b0 l
b0 t
b11010100100100 k
b11010100100100 s
b0 j
b0 x
b11010100100100 i
b11010100100100 w
b0 ~
b0 ("
b11010100100100 }
b11010100100100 '"
b0 |
b0 ,"
b11010100100100 {
b11010100100100 +"
b0 D"
b0 L"
b11010100100100 C"
b11010100100100 K"
b0 B"
b0 P"
b11010100100100 A"
b11010100100100 O"
b0 V"
b0 ^"
b11010100100100 U"
b11010100100100 ]"
b0 T"
b0 b"
b11010100100100 S"
b11010100100100 a"
1r
1v
1&"
1*"
1J"
1N"
1\"
1`"
b1 h
b1 z
b1 @"
b1 R"
b1 V
b1 ."
b1 2
b1 4
#2
b11010100100100 '
b11010100100100 K
b11010100100100 B
b11010100100100 d
b0 (
b0 L
b0 &
b0 J
b11010100100100 :
b11010100100100 <"
b11010100100100 \
b11010100100100 n
b0 C
b0 e
b0 A
b0 c
b11010100100100 X
b11010100100100 ""
b11010100100100 4"
b11010100100100 F"
b0 ;
b0 ="
b0 9
b0 ;"
b11010100100100 0"
b11010100100100 X"
b11010100100100 l
b11010100100100 t
b0 k
b0 s
b11010100100100 j
b11010100100100 x
b0 i
b0 w
b0 ]
b0 o
b0 [
b0 m
b11010100100100 ~
b11010100100100 ("
b0 }
b0 '"
b11010100100100 |
b11010100100100 ,"
b0 {
b0 +"
b0 Y
b0 #"
b0 W
b0 !"
b11010100100100 D"
b11010100100100 L"
b0 C"
b0 K"
b11010100100100 B"
b11010100100100 P"
b0 A"
b0 O"
b0 5"
b0 G"
b0 3"
b0 E"
b11010100100100 V"
b11010100100100 ^"
b0 U"
b0 ]"
b11010100100100 T"
b11010100100100 b"
b0 S"
b0 a"
b0 1"
b0 Y"
b0 /"
b0 W"
0r
0v
0&"
0*"
0J"
0N"
0\"
0`"
b10 h
b10 z
b10 @"
b10 R"
b10 V
b10 ."
b10 2
b10 4
#3
b0 '
b0 K
b11010100100100 &
b11010100100100 J
b0 B
b0 d
b11010100100100 A
b11010100100100 c
b0 :
b0 <"
b11010100100100 9
b11010100100100 ;"
b0 \
b0 n
b11010100100100 [
b11010100100100 m
b0 X
b0 ""
b11010100100100 W
b11010100100100 !"
b0 4"
b0 F"
b11010100100100 3"
b11010100100100 E"
b0 0"
b0 X"
b11010100100100 /"
b11010100100100 W"
b0 l
b0 t
b11010100100100 k
b11010100100100 s
b0 j
b0 x
b11010100100100 i
b11010100100100 w
b0 ~
b0 ("
b11010100100100 }
b11010100100100 '"
b0 |
b0 ,"
b11010100100100 {
b11010100100100 +"
b0 D"
b0 L"
b11010100100100 C"
b11010100100100 K"
b0 B"
b0 P"
b11010100100100 A"
b11010100100100 O"
b0 V"
b0 ^"
b11010100100100 U"
b11010100100100 ]"
b0 T"
b0 b"
b11010100100100 S"
b11010100100100 a"
1r
1v
1&"
1*"
1J"
1N"
1\"
1`"
b11 h
b11 z
b11 @"
b11 R"
b11 V
b11 ."
b11 2
b11 4
#4
b11010100100100 %
b11010100100100 I
b11010100100100 @
b11010100100100 b
b0 $
b0 H
b11010100100100 8
b11010100100100 :"
b11010100100100 ^
b11010100100100 p
b11010100100100 Z
b11010100100100 $"
b0 ?
b0 a
b11010100100100 6"
b11010100100100 H"
b11010100100100 2"
b11010100100100 Z"
b0 7
b0 9"
b11010100100100 l
b11010100100100 t
b0 k
b0 s
b11010100100100 j
b11010100100100 x
b0 i
b0 w
b0 ]
b0 o
b0 [
b0 m
b11010100100100 ~
b11010100100100 ("
b0 }
b0 '"
b11010100100100 |
b11010100100100 ,"
b0 {
b0 +"
b0 Y
b0 #"
b0 W
b0 !"
b0 &
b0 J
b0 "
b0 F
b11010100100100 D"
b11010100100100 L"
b0 C"
b0 K"
b11010100100100 B"
b11010100100100 P"
b0 A"
b0 O"
b0 5"
b0 G"
b0 3"
b0 E"
b11010100100100 V"
b11010100100100 ^"
b0 U"
b0 ]"
b11010100100100 T"
b11010100100100 b"
b0 S"
b0 a"
b0 1"
b0 Y"
b0 /"
b0 W"
0r
0v
0&"
0*"
b0 A
b0 c
b0 =
b0 _
0J"
0N"
0\"
0`"
b0 9
b0 ;"
b0 5
b0 7"
b0 h
b0 z
b0 @"
b0 R"
b100 V
b100 ."
b100 2
b100 4
#5
b0 %
b0 I
b11010100100100 $
b11010100100100 H
b0 @
b0 b
b11010100100100 ?
b11010100100100 a
b0 8
b0 :"
b11010100100100 7
b11010100100100 9"
b0 ^
b0 p
b11010100100100 ]
b11010100100100 o
b0 Z
b0 $"
b11010100100100 Y
b11010100100100 #"
b0 6"
b0 H"
b11010100100100 5"
b11010100100100 G"
b0 2"
b0 Z"
b11010100100100 1"
b11010100100100 Y"
b0 l
b0 t
b11010100100100 k
b11010100100100 s
b0 j
b0 x
b11010100100100 i
b11010100100100 w
b0 ~
b0 ("
b11010100100100 }
b11010100100100 '"
b0 |
b0 ,"
b11010100100100 {
b11010100100100 +"
b0 D"
b0 L"
b11010100100100 C"
b11010100100100 K"
b0 B"
b0 P"
b11010100100100 A"
b11010100100100 O"
b0 V"
b0 ^"
b11010100100100 U"
b11010100100100 ]"
b0 T"
b0 b"
b11010100100100 S"
b11010100100100 a"
1r
1v
1&"
1*"
1J"
1N"
1\"
1`"
b1 h
b1 z
b1 @"
b1 R"
b101 V
b101 ."
b101 2
b101 4
#6
b11010100100100 #
b11010100100100 G
b11010100100100 >
b11010100100100 `
b0 $
b0 H
b0 "
b0 F
b11010100100100 6
b11010100100100 8"
b11010100100100 \
b11010100100100 n
b11010100100100 X
b11010100100100 ""
b0 ?
b0 a
b0 =
b0 _
b11010100100100 4"
b11010100100100 F"
b11010100100100 0"
b11010100100100 X"
b0 7
b0 9"
b0 5
b0 7"
b11010100100100 l
b11010100100100 t
b0 k
b0 s
b11010100100100 j
b11010100100100 x
b0 i
b0 w
b0 ]
b0 o
b0 [
b0 m
b11010100100100 ~
b11010100100100 ("
b0 }
b0 '"
b11010100100100 |
b11010100100100 ,"
b0 {
b0 +"
b0 Y
b0 #"
b0 W
b0 !"
b11010100100100 D"
b11010100100100 L"
b0 C"
b0 K"
b11010100100100 B"
b11010100100100 P"
b0 A"
b0 O"
b0 5"
b0 G"
b0 3"
b0 E"
b11010100100100 V"
b11010100100100 ^"
b0 U"
b0 ]"
b11010100100100 T"
b11010100100100 b"
b0 S"
b0 a"
b0 1"
b0 Y"
b0 /"
b0 W"
0r
0v
0&"
0*"
0J"
0N"
0\"
0`"
b10 h
b10 z
b10 @"
b10 R"
b110 V
b110 ."
b110 2
b110 4
#7
b0 #
b0 G
b11010100100100 "
b11010100100100 F
b0 >
b0 `
b11010100100100 =
b11010100100100 _
b0 6
b0 8"
b11010100100100 5
b11010100100100 7"
b0 \
b0 n
b11010100100100 [
b11010100100100 m
b0 X
b0 ""
b11010100100100 W
b11010100100100 !"
b0 4"
b0 F"
b11010100100100 3"
b11010100100100 E"
b0 0"
b0 X"
b11010100100100 /"
b11010100100100 W"
b0 l
b0 t
b11010100100100 k
b11010100100100 s
b0 j
b0 x
b11010100100100 i
b11010100100100 w
b0 ~
b0 ("
b11010100100100 }
b11010100100100 '"
b0 |
b0 ,"
b11010100100100 {
b11010100100100 +"
b0 D"
b0 L"
b11010100100100 C"
b11010100100100 K"
b0 B"
b0 P"
b11010100100100 A"
b11010100100100 O"
b0 V"
b0 ^"
b11010100100100 U"
b11010100100100 ]"
b0 T"
b0 b"
b11010100100100 S"
b11010100100100 a"
1r
1v
1&"
1*"
1J"
1N"
1\"
1`"
b11 h
b11 z
b11 @"
b11 R"
b111 V
b111 ."
b111 2
b111 4
#8
b11010100100100 !
b11010100100100 E
b11010100100100 D
b11010100100100 f
b11010100100100 <
b11010100100100 >"
b0 /
b0 S
b11010100100100 ^
b11010100100100 p
b0 C
b0 e
b11010100100100 Z
b11010100100100 $"
b11010100100100 6"
b11010100100100 H"
b0 ;
b0 ="
b11010100100100 2"
b11010100100100 Z"
b11010100100100 l
b11010100100100 t
b0 k
b0 s
b11010100100100 j
b11010100100100 x
b0 i
b0 w
b0 ]
b0 o
b0 [
b0 m
b11010100100100 ~
b11010100100100 ("
b0 }
b0 '"
b11010100100100 |
b11010100100100 ,"
b0 {
b0 +"
b0 Y
b0 #"
b0 W
b0 !"
b11010100100100 D"
b11010100100100 L"
b0 C"
b0 K"
b11010100100100 B"
b11010100100100 P"
b0 A"
b0 O"
b0 5"
b0 G"
b0 3"
b0 E"
b11010100100100 V"
b11010100100100 ^"
b0 U"
b0 ]"
b11010100100100 T"
b11010100100100 b"
b0 S"
b0 a"
b0 1"
b0 Y"
b0 /"
b0 W"
b0 -
b0 Q
0r
0v
0&"
0*"
b0 A
b0 c
b0 =
b0 _
0J"
0N"
0\"
0`"
b0 9
b0 ;"
b0 5
b0 7"
b0 h
b0 z
b0 @"
b0 R"
b0 "
b0 F
b0 )
b0 M
b0 V
b0 ."
b1000 2
b1000 4
#9
b0 !
b0 E
b11010100100100 /
b11010100100100 S
b0 D
b0 f
b11010100100100 C
b11010100100100 e
b0 <
b0 >"
b11010100100100 ;
b11010100100100 ="
b0 ^
b0 p
b11010100100100 ]
b11010100100100 o
b0 Z
b0 $"
b11010100100100 Y
b11010100100100 #"
b0 6"
b0 H"
b11010100100100 5"
b11010100100100 G"
b0 2"
b0 Z"
b11010100100100 1"
b11010100100100 Y"
b0 l
b0 t
b11010100100100 k
b11010100100100 s
b0 j
b0 x
b11010100100100 i
b11010100100100 w
b0 ~
b0 ("
b11010100100100 }
b11010100100100 '"
b0 |
b0 ,"
b11010100100100 {
b11010100100100 +"
b0 D"
b0 L"
b11010100100100 C"
b11010100100100 K"
b0 B"
b0 P"
b11010100100100 A"
b11010100100100 O"
b0 V"
b0 ^"
b11010100100100 U"
b11010100100100 ]"
b0 T"
b0 b"
b11010100100100 S"
b11010100100100 a"
1r
1v
1&"
1*"
1J"
1N"
1\"
1`"
b1 h
b1 z
b1 @"
b1 R"
b1 V
b1 ."
b1001 2
b1001 4
#10
b11010100100100 .
b11010100100100 R
b11010100100100 B
b11010100100100 d
b11010100100100 :
b11010100100100 <"
b0 /
b0 S
b0 -
b0 Q
b11010100100100 \
b11010100100100 n
b0 C
b0 e
b0 A
b0 c
b11010100100100 X
b11010100100100 ""
b11010100100100 4"
b11010100100100 F"
b0 ;
b0 ="
b0 9
b0 ;"
b11010100100100 0"
b11010100100100 X"
b11010100100100 l
b11010100100100 t
b0 k
b0 s
b11010100100100 j
b11010100100100 x
b0 i
b0 w
b0 ]
b0 o
b0 [
b0 m
b11010100100100 ~
b11010100100100 ("
b0 }
b0 '"
b11010100100100 |
b11010100100100 ,"
b0 {
b0 +"
b0 Y
b0 #"
b0 W
b0 !"
b11010100100100 D"
b11010100100100 L"
b0 C"
b0 K"
b11010100100100 B"
b11010100100100 P"
b0 A"
b0 O"
b0 5"
b0 G"
b0 3"
b0 E"
b11010100100100 V"
b11010100100100 ^"
b0 U"
b0 ]"
b11010100100100 T"
b11010100100100 b"
b0 S"
b0 a"
b0 1"
b0 Y"
b0 /"
b0 W"
0r
0v
0&"
0*"
0J"
0N"
0\"
0`"
b10 h
b10 z
b10 @"
b10 R"
b10 V
b10 ."
b1010 2
b1010 4
#11
b0 .
b0 R
b11010100100100 -
b11010100100100 Q
b0 B
b0 d
b11010100100100 A
b11010100100100 c
b0 :
b0 <"
b11010100100100 9
b11010100100100 ;"
b0 \
b0 n
b11010100100100 [
b11010100100100 m
b0 X
b0 ""
b11010100100100 W
b11010100100100 !"
b0 4"
b0 F"
b11010100100100 3"
b11010100100100 E"
b0 0"
b0 X"
b11010100100100 /"
b11010100100100 W"
b0 l
b0 t
b11010100100100 k
b11010100100100 s
b0 j
b0 x
b11010100100100 i
b11010100100100 w
b0 ~
b0 ("
b11010100100100 }
b11010100100100 '"
b0 |
b0 ,"
b11010100100100 {
b11010100100100 +"
b0 D"
b0 L"
b11010100100100 C"
b11010100100100 K"
b0 B"
b0 P"
b11010100100100 A"
b11010100100100 O"
b0 V"
b0 ^"
b11010100100100 U"
b11010100100100 ]"
b0 T"
b0 b"
b11010100100100 S"
b11010100100100 a"
1r
1v
1&"
1*"
1J"
1N"
1\"
1`"
b11 h
b11 z
b11 @"
b11 R"
b11 V
b11 ."
b1011 2
b1011 4
#12
b11010100100100 ,
b11010100100100 P
b11010100100100 @
b11010100100100 b
b11010100100100 8
b11010100100100 :"
b0 +
b0 O
b11010100100100 ^
b11010100100100 p
b11010100100100 Z
b11010100100100 $"
b0 ?
b0 a
b11010100100100 6"
b11010100100100 H"
b11010100100100 2"
b11010100100100 Z"
b0 7
b0 9"
b11010100100100 l
b11010100100100 t
b0 k
b0 s
b11010100100100 j
b11010100100100 x
b0 i
b0 w
b0 ]
b0 o
b0 [
b0 m
b11010100100100 ~
b11010100100100 ("
b0 }
b0 '"
b11010100100100 |
b11010100100100 ,"
b0 {
b0 +"
b0 Y
b0 #"
b0 W
b0 !"
b11010100100100 D"
b11010100100100 L"
b0 C"
b0 K"
b11010100100100 B"
b11010100100100 P"
b0 A"
b0 O"
b0 5"
b0 G"
b0 3"
b0 E"
b11010100100100 V"
b11010100100100 ^"
b0 U"
b0 ]"
b11010100100100 T"
b11010100100100 b"
b0 S"
b0 a"
b0 1"
b0 Y"
b0 /"
b0 W"
b0 -
b0 Q
b0 )
b0 M
0r
0v
0&"
0*"
b0 A
b0 c
b0 =
b0 _
0J"
0N"
0\"
0`"
b0 9
b0 ;"
b0 5
b0 7"
b0 h
b0 z
b0 @"
b0 R"
b100 V
b100 ."
b1100 2
b1100 4
#13
b0 ,
b0 P
b11010100100100 +
b11010100100100 O
b0 @
b0 b
b11010100100100 ?
b11010100100100 a
b0 8
b0 :"
b11010100100100 7
b11010100100100 9"
b0 ^
b0 p
b11010100100100 ]
b11010100100100 o
b0 Z
b0 $"
b11010100100100 Y
b11010100100100 #"
b0 6"
b0 H"
b11010100100100 5"
b11010100100100 G"
b0 2"
b0 Z"
b11010100100100 1"
b11010100100100 Y"
b0 l
b0 t
b11010100100100 k
b11010100100100 s
b0 j
b0 x
b11010100100100 i
b11010100100100 w
b0 ~
b0 ("
b11010100100100 }
b11010100100100 '"
b0 |
b0 ,"
b11010100100100 {
b11010100100100 +"
b0 D"
b0 L"
b11010100100100 C"
b11010100100100 K"
b0 B"
b0 P"
b11010100100100 A"
b11010100100100 O"
b0 V"
b0 ^"
b11010100100100 U"
b11010100100100 ]"
b0 T"
b0 b"
b11010100100100 S"
b11010100100100 a"
1r
1v
1&"
1*"
1J"
1N"
1\"
1`"
b1 h
b1 z
b1 @"
b1 R"
b101 V
b101 ."
b1101 2
b1101 4
