Documents/CS - UTEC/ARQUITECTURA/Oyague_Macarena_L04/1/greaterOrEqualTo6.v
module greaterOrEqualTo6(input [2:0]y,
                         output reg z1);
    always @ (y[2] or y[1] or y[0])
    begin
      if (y[2] & y[1])
        z1 = 1'b1;
      else
         z1 = 1'b0;
    end
endmodule

Documents/CS - UTEC/ARQUITECTURA/Oyague_Macarena_L04/1/greaterOrEqualTo6_tb.v
`timescale 1ns/1ns
module greaterOrEqualTo6_tb;
    reg [2:0]y;
    wire z1;
    greaterOrEqualTo6 mod(.y(y), .z1(z1));
    initial begin
        y = 3'b000;
        $monitor("%d ns:\ty=%b\t z1=%b", $time, y, z1);
        #10 $finish;
    end
    always #1 y = y + 1'h1; 
    initial begin
        $dumpfile("greaterOrEqualTo6.vcd");
        $dumpvars;
    end
endmodule

Documents/CS - UTEC/ARQUITECTURA/Oyague_Macarena_L04/1/greaterOrEqualTo6.vcd
$date
	Sun May 31 22:08:44 2020
$end
$version
	Icarus Verilog
$end
$timescale
	1ns
$end
$scope module greaterOrEqualTo6_tb $end
$var wire 1 ! z1 $end
$var reg 3 " y [2:0] $end
$scope module mod $end
$var wire 3 # y [2:0] $end
$var reg 1 ! z1 $end
$upscope $end
$upscope $end
$enddefinitions $end
#0
$dumpvars
b0 #
b0 "
0!
$end
#1
b1 "
b1 #
#2
b10 "
b10 #
#3
b11 "
b11 #
#4
b100 "
b100 #
#5
b101 "
b101 #
#6
1!
b110 "
b110 #
#7
b111 "
b111 #
#8
0!
b0 "
b0 #
#9
b1 "
b1 #
#10
b10 "
b10 #
