Documents/CS - UTEC/ARQUITECTURA/Oyague_Macarena_L02/4/decoder_3_8.v
module decoder3_8 (  input [2:0]input1,
                      input enable,
                      output [7:0]output1);
    assign output1[0] = enable == 1 ? (input1 == 3'b000 ? 1 : 0) : 0;
    assign output1[1] = enable == 1 ? (input1 == 3'b001 ? 1 : 0) : 0;
    assign output1[2] = enable == 1 ? (input1 == 3'b010 ? 1 : 0) : 0;
    assign output1[3] = enable == 1 ? (input1 == 3'b011 ? 1 : 0) : 0;
    assign output1[4] = enable == 1 ? (input1 == 3'b100 ? 1 : 0) : 0;
    assign output1[5] = enable == 1 ? (input1 == 3'b101 ? 1 : 0) : 0;
    assign output1[6] = enable == 1 ? (input1 == 3'b110 ? 1 : 0) : 0;
    assign output1[7] = enable == 1 ? (input1 == 3'b111 ? 1 : 0) : 0;
endmodule

Documents/CS - UTEC/ARQUITECTURA/Oyague_Macarena_L02/4/decoder_3_8_tb.v
`timescale 1ns/1ns
module decoder3_8_tb;
    reg [2:0]input1;
    reg enable;
    wire [7:0]output1;
    decoder3_8 decoder(input1, enable, output1);
    initial begin
        input1[0] = 0;
        input1[1] = 0;
        input1[2] = 0;
        enable = 1;
        $monitor("%d ns:\tin[0]=%b in[1]=%b in[2]=%b\tout[0]=%h  out[1]=%h  out[2]=%h  out[3]=%h  out[4]=%h  out[5]=%h  out[6]=%h  out[7]=%h", 
                $time, input1[0], input1[1], input1[2], output1[0], output1[1], output1[2], output1[3],  output1[4], output1[5], output1[6], output1[7]);
        #9 $finish;
    end
    always #1 input1[0]=!input1[0];
    always #2 input1[1]=!input1[1];
    always #4 input1[2]=!input1[2];
    always #8 enable=!enable;
    initial begin
        $dumpfile("decoder_3_8.vcd");
        $dumpvars;
    end
endmodule

Documents/CS - UTEC/ARQUITECTURA/Oyague_Macarena_L02/4/decoder_3_8.vcd
$date
	Thu May  7 20:26:29 2020
$end
$version
	Icarus Verilog
$end
$timescale
	1ns
$end
$scope module decoder3_8_tb $end
$var wire 8 ! output1 [7:0] $end
$var reg 1 " enable $end
$var reg 3 # input1 [2:0] $end
$scope module decoder $end
$var wire 1 " enable $end
$var wire 3 $ input1 [2:0] $end
$var wire 8 % output1 [7:0] $end
$upscope $end
$upscope $end
$enddefinitions $end
#0
$dumpvars
b1 %
b0 $
b0 #
1"
b1 !
$end
#1
b10 !
b10 %
b1 #
b1 $
#2
b100 !
b100 %
b10 #
b10 $
#3
b1000 !
b1000 %
b11 #
b11 $
#4
b10000 !
b10000 %
b100 #
b100 $
#5
b100000 !
b100000 %
b101 #
b101 $
#6
b1000000 !
b1000000 %
b110 #
b110 $
#7
b10000000 !
b10000000 %
b111 #
b111 $
#8
b0 !
b0 %
b0 #
b0 $
0"
#9
b1 #
b1 $
