Documents/CS - UTEC/ARQUITECTURA/LAB 3 PRIMER INTENTO/Oyague_Macarena_L03/1/Behav/DLatch.v
module DLatch(     input o1,
                   input clrn,
                   input clk,
                   input o2,
                   input prn,
                   output q,
                   output qn);
    assign q = (o1 & clrn & clk) & prn & qn;
    assign qn = (o2 & prn & clk) & q & clrn;
endmodule

Documents/CS - UTEC/ARQUITECTURA/Oyague_Macarena_L03/1/Behav/JKFF.v
`include "DLatch.v"
module JKFF(  input prn,
              input j,
              input k,
              input clk,
              input clrn,
              output q,
              output qn);
    wire o1, o2;
    JKLatch jkl(prn, j, k, ~clk, clrn, q, qn, o1, o2);
    DLatch dl(o1, clrn, clk, o2, prn, q, qn);
endmodule

module JKLatch(    input prn,
                   input j,
                   input k,
                   input clkn,
                   input clrn,
                   input q,
                   input qn,
                   output o1,
                   output o2);
    assign o1 = (qn & j & clkn & clrn) & prn & o2;
    assign o2 = o1 & clrn & (prn & clkn & k & q);
endmodule

Documents/CS - UTEC/ARQUITECTURA/Oyague_Macarena_L03/1/Behav/JKFF_tb.v
`timescale 1ns/1ns
module JKFF_tb;
    reg prn, j, k, clk, clrn;
    wire q, qn;
    JKFF jkflipflop(prn, j, k, clk, clrn, q, qn);
    initial begin
        clk = 1;
        clrn = 0;
        prn = 0;
        j = 1;
        k = 1;
        $monitor("%d ns:\tprn=%b  j=%b  k=%b  clk=%b  clrn=%b  q=%b  qn=%b", 
                 $time, prn, j, k, clk, clrn, q, qn);
        #20 $finish;
    end
    always #1 clk = !clk;
    always #1 clrn = 1;
    always #1 prn = 1;
    always #2 j = !j;
    always #4 k = !k;
    initial begin
        $dumpfile("JKFF.vcd");
        $dumpvars;
    end
endmodule

Documents/CS - UTEC/ARQUITECTURA/Oyague_Macarena_L03/1/Behav/JKFF.vcd
$date
	Sun May 17 01:31:23 2020
$end
$version
	Icarus Verilog
$end
$timescale
	1ns
$end
$scope module JKFF_tb $end
$var wire 1 ! qn $end
$var wire 1 " q $end
$var reg 1 # clk $end
$var reg 1 $ clrn $end
$var reg 1 % j $end
$var reg 1 & k $end
$var reg 1 ' prn $end
$scope module jkflipflop $end
$var wire 1 # clk $end
$var wire 1 $ clrn $end
$var wire 1 % j $end
$var wire 1 & k $end
$var wire 1 ' prn $end
$var wire 1 ! qn $end
$var wire 1 " q $end
$var wire 1 ( o2 $end
$var wire 1 ) o1 $end
$scope module dl $end
$var wire 1 # clk $end
$var wire 1 $ clrn $end
$var wire 1 ' prn $end
$var wire 1 " q $end
$var wire 1 ! qn $end
$var wire 1 ( o2 $end
$var wire 1 ) o1 $end
$upscope $end
$scope module jkl $end
$var wire 1 * clkn $end
$var wire 1 $ clrn $end
$var wire 1 % j $end
$var wire 1 & k $end
$var wire 1 ) o1 $end
$var wire 1 ( o2 $end
$var wire 1 ' prn $end
$var wire 1 " q $end
$var wire 1 ! qn $end
$upscope $end
$upscope $end
$upscope $end
$enddefinitions $end
#0
$dumpvars
0*
0)
0(
0'
1&
1%
0$
1#
0"
0!
$end
#1
1*
1'
1$
0#
#2
0*
1#
0%
#3
1*
0#
#4
0*
1#
1%
0&
#5
1*
0#
#6
0*
1#
0%
#7
1*
0#
#8
0*
1#
1%
1&
#9
1*
0#
#10
0*
1#
0%
#11
1*
0#
#12
0*
1#
1%
0&
#13
1*
0#
#14
0*
1#
0%
#15
1*
0#
#16
0*
1#
1%
1&
#17
1*
0#
#18
0*
1#
0%
#19
1*
0#
#20
0*
1#
1%
0&
