Documents/CS - UTEC/ARQUITECTURA/Oyague_Macarena_L03/3/RSLatch.v
module RSLatch(    input s,
                   input r, 
                   input clr,
                   output reg q, 
                   output reg qn);
    always@(*)
        begin
            if (clr == 1'b1) begin q <= 0; qn <= 0; end
            else 
                begin
                if (s == 1'b1 & r == 1'b0) begin q <= 1; qn <= 0; end
                else if (s == 1'b0 & r == 1'b1) begin q <= 0; qn <= 1; end
                else if (s == 1'b1 & r == 1'b1) begin q <= 0; qn <= 0; end
                end
        end
endmodule

Documents/CS - UTEC/ARQUITECTURA/Oyague_Macarena_L03/3/RSLatch_tb.v
`timescale 1ns/1ns
module RSLatch_tb;
    reg s, r, clr;
    wire q, qn;
    RSLatch latch(s, r, clr, q, qn);
    initial begin
        s = 0;
        r = 0;
        clr = 1;
        $display("time\ten\tn\td\t");
        $monitor("%d ns:\ts=%h\tr=%h\tclr=%h\tq=%h\tqn=%h", $time, s, r, clr, q, qn);
        #10 $finish;
    end
    always #1 s = !s; //funciona con 0 0, no debería funcionar
    always #2 r = !r;
    always #1 clr = 0;
initial begin
        $dumpfile("RSLatch.vcd");
        $dumpvars;
    end
endmodule

Documents/CS - UTEC/ARQUITECTURA/Oyague_Macarena_L03/3/RSLatch.vcd
$date
	Sun May 24 16:14:32 2020
$end
$version
	Icarus Verilog
$end
$timescale
	1ns
$end
$scope module RSLatch_tb $end
$var wire 1 ! qn $end
$var wire 1 " q $end
$var reg 1 # clr $end
$var reg 1 $ r $end
$var reg 1 % s $end
$scope module latch $end
$var wire 1 # clr $end
$var wire 1 $ r $end
$var wire 1 % s $end
$var reg 1 " q $end
$var reg 1 ! qn $end
$upscope $end
$upscope $end
$enddefinitions $end
#0
$dumpvars
0%
0$
1#
0"
0!
$end
#1
1"
0#
1%
#2
1!
0"
0%
1$
#3
0!
1%
#4
0%
0$
#5
1"
1%
#6
1!
0"
0%
1$
#7
0!
1%
#8
0%
0$
#9
1"
1%
#10
1!
0"
0%
1$
