Documents/CS - UTEC/ARQUITECTURA/Oyague_Macarena_L03/2/DFF.v
module DFF(   input d,
              input clk,
              input clrn,
              output reg q);
    always@(posedge clk)
    begin
      if (clrn == 1'b0) q <= 0;
      else q <= d;
    end
endmodule

Documents/CS - UTEC/ARQUITECTURA/Oyague_Macarena_L03/2/DFF_tb.v
`timescale 1ns/1ns
module DFF_tb;
    reg d, clk, clrn;
    wire q;
    DFF dff(d, clk, clrn, q);
    initial begin
        clk = 0;
        d = 0;
        clrn = 1;
        $monitor("%d ns:\td=%h\tclk=%h\tclrn=%h\tq=%h", 
                 $time, d, clk, clrn, q);
        #15 $finish;
    end
    always #1 clk =! clk;
    always #2 d =! d;
    always #4 clrn =! clrn;
    initial begin
        $dumpfile("DFF.vcd");
        $dumpvars;
    end
endmodule

Documents/CS - UTEC/ARQUITECTURA/Oyague_Macarena_L03/2/DFF.vcd
$date
	Sun May 24 13:53:36 2020
$end
$version
	Icarus Verilog
$end
$timescale
	1ns
$end
$scope module DFF_tb $end
$var wire 1 ! q $end
$var reg 1 " clk $end
$var reg 1 # clrn $end
$var reg 1 $ d $end
$scope module dff $end
$var wire 1 " clk $end
$var wire 1 # clrn $end
$var wire 1 $ d $end
$var reg 1 ! q $end
$upscope $end
$upscope $end
$enddefinitions $end
#0
$dumpvars
0$
1#
0"
x!
$end
#1
0!
1"
#2
0"
1$
#3
1!
1"
#4
0"
0$
0#
#5
0!
1"
#6
0"
1$
#7
1"
#8
0"
0$
1#
#9
1"
#10
0"
1$
#11
1!
1"
#12
0"
0$
0#
#13
0!
1"
#14
0"
1$
