Documents/CS - UTEC/ARQUITECTURA/Oyague_Macarena_L03/2/mux_2_1.v
module mux2_1(  input d_0,
                input d_1,
                input selector,
                output out);
  assign out = selector ? d_1 : d_0;
endmodule

Documents/CS - UTEC/ARQUITECTURA/Oyague_Macarena_L03/2/mux_2_1_tb.v
`timescale 1ns/1ns
module mux2_1_tb;
    reg d_0, d_1;
    reg selector;
    wire out;
    mux2_1 mux(d_0, d_1, selector, out);
    initial begin
        selector <= 0;
        d_0 <= 0; 
        d_1 <= 0;
        $monitor("%d ns:\tselector=%b\t d_0=%h  d_1=%h \t out=%h", $time, selector, d_0, d_1, out);
        #8 $finish;
    end
    always #4 selector=!selector;
    always #1 d_0=!d_0;
    always #2 d_1=!d_1;
    initial begin
        $dumpfile("mux2_1.vcd");
        $dumpvars;
    end
endmodule

Documents/CS - UTEC/ARQUITECTURA/Oyague_Macarena_L03/2/mux2_1.vcd
$date
	Sun May 24 13:43:59 2020
$end
$version
	Icarus Verilog
$end
$timescale
	1ns
$end
$scope module mux2_1_tb $end
$var wire 1 ! out $end
$var reg 1 " d_0 $end
$var reg 1 # d_1 $end
$var reg 1 $ selector $end
$scope module mux $end
$var wire 1 " d_0 $end
$var wire 1 # d_1 $end
$var wire 1 $ selector $end
$var wire 1 ! out $end
$upscope $end
$upscope $end
$enddefinitions $end
#0
$dumpvars
0$
0#
0"
0!
$end
#1
1!
1"
#2
0!
0"
1#
#3
1!
1"
#4
0!
0"
0#
1$
#5
1"
#6
1!
0"
1#
#7
1"
#8
0!
0"
0#
0$
