Documents/CS - UTEC/ARQUITECTURA/Oyague_Macarena_L03/2/DFF.v
module DFF(   input d,
              input clk,
              input clrn,
              output reg q);
    always@(posedge clk)
    begin
      if (clrn == 1'b0) q <= 0;
      else q <= d;
    end
endmodule

Documents/CS - UTEC/ARQUITECTURA/Oyague_Macarena_L03/2/mux_2_1.v
module mux2_1(  input d_0,
                input d_1,
                input selector,
                output out);
  assign out = selector ? d_1 : d_0;
endmodule

Documents/CS - UTEC/ARQUITECTURA/Oyague_Macarena_L03/2/SchematicMisterioso.v
`include "mux_2_1.v"
`include "DFF.v"
module SchematicMisterioso(   input [2:0]d,
                              input di,
                              input load,
                              input clk,
                              input clrn,
                              output [2:0]q,
                              output do);
    wire mout1, mout2, mout3;
    mux2_1 m1(.d_0(di), .d_1(d[2]), .selector(load), .out(mout1));
    DFF d1(.d(mout1), .clk(clk), .clrn(clrn), .q(q[2]));
    mux2_1 m2(.d_0(q[2]), .d_1(d[1]), .selector(load), .out(mout2));
    DFF d2(.d(mout2), .clk(clk), .clrn(clrn), .q(q[1]));
    mux2_1 m3(.d_0(q[1]), .d_1(d[0]), .selector(load), .out(mout3));
    DFF d3(.d(mout3), .clk(clk), .clrn(clrn), .q(q[0]));
    assign do = q[0];
endmodule

Documents/CS - UTEC/ARQUITECTURA/Oyague_Macarena_L03/2/SchematicMisterioso_tb.v
`timescale 1ns/1ns
module SchematicMisterioso_tb;
    reg [2:0]d;
    reg di, load, clk, clrn;
    wire [2:0]q;
    wire do;
    SchematicMisterioso SM(d, di, load, clk, clrn, q, do);
    initial begin
        clk = 0;
        di = 1;
        d = 3'b101;
        clrn = 0;
        load = 0;
        $monitor("%d ns:  d=%b  di=%b  load=%b  clk=%b  clrn=%b  q=%b  do=%b", 
                 $time, d, di, load, clk, clrn, q, do);
        #9 $finish;
    end
    always #1 clk =! clk;
    always #8 load =! load;
    always #2 clrn = 1;
    initial begin
        $dumpfile("SM.vcd");
        $dumpvars;
    end
endmodule

Documents/CS - UTEC/ARQUITECTURA/Oyague_Macarena_L03/2/SM.vcd
$date
	Sun May 24 15:45:43 2020
$end
$version
	Icarus Verilog
$end
$timescale
	1ns
$end
$scope module SchematicMisterioso_tb $end
$var wire 3 ! q [2:0] $end
$var wire 1 " do $end
$var reg 1 # clk $end
$var reg 1 $ clrn $end
$var reg 3 % d [2:0] $end
$var reg 1 & di $end
$var reg 1 ' load $end
$scope module SM $end
$var wire 1 # clk $end
$var wire 1 $ clrn $end
$var wire 3 ( d [2:0] $end
$var wire 1 & di $end
$var wire 1 ' load $end
$var wire 3 ) q [2:0] $end
$var wire 1 * mout3 $end
$var wire 1 + mout2 $end
$var wire 1 , mout1 $end
$var wire 1 " do $end
$scope module d1 $end
$var wire 1 # clk $end
$var wire 1 $ clrn $end
$var wire 1 , d $end
$var reg 1 - q $end
$upscope $end
$scope module d2 $end
$var wire 1 # clk $end
$var wire 1 $ clrn $end
$var wire 1 + d $end
$var reg 1 . q $end
$upscope $end
$scope module d3 $end
$var wire 1 # clk $end
$var wire 1 $ clrn $end
$var wire 1 * d $end
$var reg 1 / q $end
$upscope $end
$scope module m1 $end
$var wire 1 & d_0 $end
$var wire 1 0 d_1 $end
$var wire 1 ' selector $end
$var wire 1 , out $end
$upscope $end
$scope module m2 $end
$var wire 1 1 d_0 $end
$var wire 1 2 d_1 $end
$var wire 1 ' selector $end
$var wire 1 + out $end
$upscope $end
$scope module m3 $end
$var wire 1 3 d_0 $end
$var wire 1 4 d_1 $end
$var wire 1 ' selector $end
$var wire 1 * out $end
$upscope $end
$upscope $end
$upscope $end
$enddefinitions $end
#0
$dumpvars
14
x3
02
x1
10
x/
x.
x-
1,
x+
x*
bx )
b101 (
0'
1&
b101 %
0$
0#
x"
bx !
$end
#1
0+
0*
01
03
0"
0-
0.
b0 !
b0 )
0/
1#
#2
0#
1$
#3
1+
11
b100 !
b100 )
1-
1#
#4
0#
#5
1*
13
b110 !
b110 )
1.
1#
#6
0#
#7
1"
b111 !
b111 )
1/
1#
#8
0+
0#
1'
#9
03
b101 !
b101 )
0.
1#
