Documents/CS - UTEC/ARQUITECTURA/LAB 3 PRIMER INTENTO/Oyague_Macarena_L03/3/DFF.v
module DFF(   input d,
              input clk,
              input clr,
              output q);
    assign q = clr ? 0 : (clk == 0 ? q : (d == 0 ? 0 : 1));
endmodule

Documents/CS - UTEC/ARQUITECTURA/LAB 3 PRIMER INTENTO/Oyague_Macarena_L03/3/DFF_tb.v
`timescale 1ns/1ns
module DFF_tb;
    reg d, clk, clr;
    wire q;
    DFF dff(d, clk, clr, q);
    initial begin
        clk = 1;
        d = 0;
        clr = 0;
        $monitor("%d ns:\td=%h\tclk=%h\tclr=%h\tq=%h", 
                 $time, d, clk, clr, q);
        #20 $finish;
    end
    always #1 d =! d;
    always #2 clk =! clk;
    always #4 clr =! clr;
    initial begin
        $dumpfile("DFF.vcd");
        $dumpvars;
    end
endmodule

Documents/CS - UTEC/ARQUITECTURA/LAB 3 PRIMER INTENTO/Oyague_Macarena_L03/3/DFF.vcd
$date
	Sat May 16 13:59:20 2020
$end
$version
	Icarus Verilog
$end
$timescale
	1ns
$end
$scope module DFF_tb $end
$var wire 1 ! q $end
$var reg 1 " clk $end
$var reg 1 # clr $end
$var reg 1 $ d $end
$scope module dff $end
$var wire 1 " clk $end
$var wire 1 # clr $end
$var wire 1 $ d $end
$var wire 1 ! q $end
$upscope $end
$upscope $end
$enddefinitions $end
#0
$dumpvars
0$
0#
1"
0!
$end
#1
1!
1$
#2
0$
0"
#3
1$
#4
0!
0$
1"
1#
#5
1$
#6
0$
0"
#7
1$
#8
0!
0$
1"
0#
#9
1!
1$
#10
0$
0"
#11
1$
#12
0!
0$
1"
1#
#13
1$
#14
0$
0"
#15
1$
#16
0!
0$
1"
0#
#17
1!
1$
#18
0$
0"
#19
1$
#20
0!
0$
1"
1#
