Documents/CS - UTEC/ARQUITECTURA/Oyague_Macarena_L04/4/Thunderbird.v
module FSMBehavioral (input reset, clk, R, L,
                      output LC, LB, LA, RA, RB, RC, 
                      output reg[2:0]y);

reg [2:0] next_state;

parameter a = 3'b000, b = 3'b001, c = 3'b010, d = 3'b011, 
          e = 3'b100, f = 3'b101, g = 3'b111;

assign LC = (y==d);
assign LB = (y==c | y==d);
assign LA = (y==b | y==c | y==d);
assign RA = (y==e | y==f | y==g);
assign RB = (y==f | y==g);
assign RC = (y==g);

always @ (posedge clk)
begin
    if (reset)
        y = a;
    else
        y = next_state;
end

always @ (y or L or R)
begin
    case (y)
    a:
        if (L) next_state = b;
        else if (R) next_state = e;
    b: 
        next_state = c;
    c:
        next_state = d;
    d:
        next_state = a;
    e: 
        next_state = f;
    f:
        next_state = g;
    g:
        next_state = a;
    default:
        next_state = a;
    endcase
end
endmodule

Documents/CS - UTEC/ARQUITECTURA/Oyague_Macarena_L04/4/Thunderbird_tb.v
module Thunderbird_tb;

    reg reset, clk, R, L;
    wire [2:0]y;
    wire LC, LB, LA, RA, RB, RC;

    FSMBehavioral fsm(.reset(reset), .clk(clk), .R(R), .L(L),
                      .LC(LC), .LB(LB), .LA(LA), 
                      .RA(RA), .RB(RB), .RC(RC), 
                      .y(y));
    initial begin
        clk = 0;
        reset = 1;         
        L = 0;
        R = 0;
        #1 reset = 0;
        #1 R = 1;
        #8 L = 1;     
        #16 $finish;
    end

    initial begin
        $monitor("%d ns:\tL=%b \tR=%b \t LEFT=%b%b%b\t RIGHT=%b%b%b\t y=%b", $time, L, R, LC, LB, LA, RA, RB, RC, y);
    end
    
    always #1 clk = !clk;

    initial begin
        $dumpfile("Thunderbird.vcd");
        $dumpvars;
    end
endmodule

Documents/CS - UTEC/ARQUITECTURA/Oyague_Macarena_L04/4/Thunderbird.vcd
$date
	Sun May 31 22:45:42 2020
$end
$version
	Icarus Verilog
$end
$timescale
	1s
$end
$scope module Thunderbird_tb $end
$var wire 3 ! y [2:0] $end
$var wire 1 " RC $end
$var wire 1 # RB $end
$var wire 1 $ RA $end
$var wire 1 % LC $end
$var wire 1 & LB $end
$var wire 1 ' LA $end
$var reg 1 ( L $end
$var reg 1 ) R $end
$var reg 1 * clk $end
$var reg 1 + reset $end
$scope module fsm $end
$var wire 1 ( L $end
$var wire 1 ' LA $end
$var wire 1 & LB $end
$var wire 1 ) R $end
$var wire 1 $ RA $end
$var wire 1 # RB $end
$var wire 1 * clk $end
$var wire 1 + reset $end
$var wire 1 " RC $end
$var wire 1 % LC $end
$var reg 3 , next_state [2:0] $end
$var reg 3 - y [2:0] $end
$upscope $end
$upscope $end
$enddefinitions $end
#0
$dumpvars
bx -
b0 ,
1+
0*
0)
0(
x'
x&
x%
x$
x#
x"
bx !
$end
#1
0'
0$
0&
0#
0%
0"
b0 !
b0 -
1*
0+
#2
b100 ,
0*
1)
#3
1$
b101 ,
b100 !
b100 -
1*
#4
0*
#5
b111 ,
1#
b101 !
b101 -
1*
#6
0*
#7
b0 ,
1"
b111 !
b111 -
1*
#8
0*
#9
b100 ,
0$
0#
0"
b0 !
b0 -
1*
#10
b1 ,
0*
1(
#11
1'
b10 ,
b1 !
b1 -
1*
#12
0*
#13
b11 ,
1&
b10 !
b10 -
1*
#14
0*
#15
b0 ,
1%
b11 !
b11 -
1*
#16
0*
#17
b1 ,
0&
0'
0%
b0 !
b0 -
1*
#18
0*
#19
1'
b10 ,
b1 !
b1 -
1*
#20
0*
#21
b11 ,
1&
b10 !
b10 -
1*
#22
0*
#23
b0 ,
1%
b11 !
b11 -
1*
#24
0*
#25
b1 ,
0&
0'
0%
b0 !
b0 -
1*
