Documents/CS - UTEC/ARQUITECTURA/Oyague_Macarena_L02/1/mux_2_1.v
module mux2_1(  input [15:0]input1,
                input [15:0]input2,
                input selector,
                output [15:0]output1);
  assign output1 = selector ? input2 : input1;
endmodule

Documents/CS - UTEC/ARQUITECTURA/Oyague_Macarena_L02/2/mux_4_1.v
`include "mux_2_1.v"
module mux4_1(  input[15:0] input1,
                input[15:0] input2,
                input[15:0] input3,
                input[15:0] input4,
                input[1:0] selector,
                output[15:0] output1);
    wire [15:0] submodule1, submodule2;
    mux2_1 mux1(input1, input2, selector[0], submodule1);
    mux2_1 mux2(input3, input4, selector[0], submodule2);
    assign output1 = selector[1] ? submodule2 : submodule1;
endmodule

Documents/CS - UTEC/ARQUITECTURA/Oyague_Macarena_L02/2/mux_8_1.v
`include "mux_4_1.v"
module mux8_1 (   input [15:0]input1,
                  input [15:0]input2,
                  input [15:0]input3,
                  input [15:0]input4,
                  input [15:0]input5,
                  input [15:0]input6,
                  input [15:0]input7,
                  input [15:0]input8,
                  input [2:0]selector,
                  output [15:0]output1);
    wire [15:0]submodule1, submodule2;
    mux4_1 mux1(input1, input2, input3, input4, selector[1:0], submodule1);
    mux4_1 mux2(input5, input6, input7, input8, selector[1:0], submodule2);
    assign output1 = selector [2] ? submodule2 : submodule1;
endmodule

Documents/CS - UTEC/ARQUITECTURA/Oyague_Macarena_L02/2/mux_16_1.v
`include "mux_8_1.v"
module mux16_1 (   input [15:0]input1,
                   input [15:0]input2,
                   input [15:0]input3,
                   input [15:0]input4,
                   input [15:0]input5,
                   input [15:0]input6,
                   input [15:0]input7,
                   input [15:0]input8,
                   input [15:0]input9,
                   input [15:0]input10,
                   input [15:0]input11,
                   input [15:0]input12,
                   input [15:0]input13,
                   input [15:0]input14,
                   input [15:0]input15,
                   input [15:0]input16,
                   input [3:0]selector,
                   output [15:0]output1);
    wire [15:0]submodule1, submodule2;
    mux8_1 mux1(input1, input2, input3, input4, input5, input6, input7, input8, selector[2:0], submodule1);
    mux8_1 mux2(input9, input10, input11, input12, input13, input14, input15, input16, selector[2:0], submodule2);
    assign output1 = selector[3] ? submodule2 : submodule1;
endmodule

Documents/CS - UTEC/ARQUITECTURA/Oyague_Macarena_L02/2/mux_16_1_tb.v
`timescale 1ns/1ns

module mux16_1_tb;
    reg [15:0]input1, input2, input3, input4, input5, input6, input7, input8, input9, input10, input11, input12, input13, input14, input15, input16;
    reg [3:0]selector;
    wire [15:0]output1;
    mux16_1 mux (input1, input2, input3, input4, input5, input6, input7, input8, input9, input10, input11, input12, input13, input14, input15, input16, selector, output1);
    initial begin
      selector[0] = 0;
      selector[1] = 0;
      selector[2] = 0;
      selector[3] = 0;
      input1=$random;
      input2=$random;
      input3=$random;
      input4=$random;
      input5=$random;
      input6=$random;
      input7=$random;
      input8=$random;
      input9=$random;
      input10=$random;
      input11=$random;
      input12=$random;
      input13=$random;
      input14=$random;
      input15=$random;
      input16=$random;
      $monitor("%d ns:\tsel[0]=%b sel[1]=%b sel[2]=%b sel[3]=%b\tin1=%h  in2=%h  in3=%h  in4=%h  in5=%h  in6=%h  in7=%h  in8=%h  in9=%h  in10=%h  in11=%h  in12=%h  in13=%h  in14=%h  in15=%h  in16=%h\tout1=%h", 
                $time, selector[0], selector[1], selector[2], selector[3], input1, input2, input3, input4, input5, input6, input7, input8, input9, input10, input11, input12, input13, input14, input15, input16, output1);
      #16 $finish;
    end
    always #1 selector[0]=!selector[0];
    always #2 selector[1]=!selector[1];
    always #4 selector[2]=!selector[2];
    always #8 selector[3]=!selector[3];
    initial begin
        $dumpfile("mux16_1.vcd");
        $dumpvars;
    end
endmodule

Documents/CS - UTEC/ARQUITECTURA/Oyague_Macarena_L02/2/mux16_1.vcd
$date
	Wed May  6 16:57:29 2020
$end
$version
	Icarus Verilog
$end
$timescale
	1ns
$end
$scope module mux16_1_tb $end
$var wire 16 ! output1 [15:0] $end
$var reg 16 " input1 [15:0] $end
$var reg 16 # input10 [15:0] $end
$var reg 16 $ input11 [15:0] $end
$var reg 16 % input12 [15:0] $end
$var reg 16 & input13 [15:0] $end
$var reg 16 ' input14 [15:0] $end
$var reg 16 ( input15 [15:0] $end
$var reg 16 ) input16 [15:0] $end
$var reg 16 * input2 [15:0] $end
$var reg 16 + input3 [15:0] $end
$var reg 16 , input4 [15:0] $end
$var reg 16 - input5 [15:0] $end
$var reg 16 . input6 [15:0] $end
$var reg 16 / input7 [15:0] $end
$var reg 16 0 input8 [15:0] $end
$var reg 16 1 input9 [15:0] $end
$var reg 4 2 selector [3:0] $end
$scope module mux $end
$var wire 16 3 input1 [15:0] $end
$var wire 16 4 input10 [15:0] $end
$var wire 16 5 input11 [15:0] $end
$var wire 16 6 input12 [15:0] $end
$var wire 16 7 input13 [15:0] $end
$var wire 16 8 input14 [15:0] $end
$var wire 16 9 input15 [15:0] $end
$var wire 16 : input16 [15:0] $end
$var wire 16 ; input2 [15:0] $end
$var wire 16 < input3 [15:0] $end
$var wire 16 = input4 [15:0] $end
$var wire 16 > input5 [15:0] $end
$var wire 16 ? input6 [15:0] $end
$var wire 16 @ input7 [15:0] $end
$var wire 16 A input8 [15:0] $end
$var wire 16 B input9 [15:0] $end
$var wire 4 C selector [3:0] $end
$var wire 16 D submodule2 [15:0] $end
$var wire 16 E submodule1 [15:0] $end
$var wire 16 F output1 [15:0] $end
$scope module mux1 $end
$var wire 16 G input1 [15:0] $end
$var wire 16 H input2 [15:0] $end
$var wire 16 I input3 [15:0] $end
$var wire 16 J input4 [15:0] $end
$var wire 16 K input5 [15:0] $end
$var wire 16 L input6 [15:0] $end
$var wire 16 M input7 [15:0] $end
$var wire 16 N input8 [15:0] $end
$var wire 3 O selector [2:0] $end
$var wire 16 P submodule2 [15:0] $end
$var wire 16 Q submodule1 [15:0] $end
$var wire 16 R output1 [15:0] $end
$scope module mux1 $end
$var wire 16 S input1 [15:0] $end
$var wire 16 T input2 [15:0] $end
$var wire 16 U input3 [15:0] $end
$var wire 16 V input4 [15:0] $end
$var wire 2 W selector [1:0] $end
$var wire 16 X submodule2 [15:0] $end
$var wire 16 Y submodule1 [15:0] $end
$var wire 16 Z output1 [15:0] $end
$scope module mux1 $end
$var wire 16 [ input1 [15:0] $end
$var wire 16 \ input2 [15:0] $end
$var wire 1 ] selector $end
$var wire 16 ^ output1 [15:0] $end
$upscope $end
$scope module mux2 $end
$var wire 16 _ input1 [15:0] $end
$var wire 16 ` input2 [15:0] $end
$var wire 1 a selector $end
$var wire 16 b output1 [15:0] $end
$upscope $end
$upscope $end
$scope module mux2 $end
$var wire 16 c input1 [15:0] $end
$var wire 16 d input2 [15:0] $end
$var wire 16 e input3 [15:0] $end
$var wire 16 f input4 [15:0] $end
$var wire 2 g selector [1:0] $end
$var wire 16 h submodule2 [15:0] $end
$var wire 16 i submodule1 [15:0] $end
$var wire 16 j output1 [15:0] $end
$scope module mux1 $end
$var wire 16 k input1 [15:0] $end
$var wire 16 l input2 [15:0] $end
$var wire 1 m selector $end
$var wire 16 n output1 [15:0] $end
$upscope $end
$scope module mux2 $end
$var wire 16 o input1 [15:0] $end
$var wire 16 p input2 [15:0] $end
$var wire 1 q selector $end
$var wire 16 r output1 [15:0] $end
$upscope $end
$upscope $end
$upscope $end
$scope module mux2 $end
$var wire 16 s input1 [15:0] $end
$var wire 16 t input2 [15:0] $end
$var wire 16 u input3 [15:0] $end
$var wire 16 v input4 [15:0] $end
$var wire 16 w input5 [15:0] $end
$var wire 16 x input6 [15:0] $end
$var wire 16 y input7 [15:0] $end
$var wire 16 z input8 [15:0] $end
$var wire 3 { selector [2:0] $end
$var wire 16 | submodule2 [15:0] $end
$var wire 16 } submodule1 [15:0] $end
$var wire 16 ~ output1 [15:0] $end
$scope module mux1 $end
$var wire 16 !" input1 [15:0] $end
$var wire 16 "" input2 [15:0] $end
$var wire 16 #" input3 [15:0] $end
$var wire 16 $" input4 [15:0] $end
$var wire 2 %" selector [1:0] $end
$var wire 16 &" submodule2 [15:0] $end
$var wire 16 '" submodule1 [15:0] $end
$var wire 16 (" output1 [15:0] $end
$scope module mux1 $end
$var wire 16 )" input1 [15:0] $end
$var wire 16 *" input2 [15:0] $end
$var wire 1 +" selector $end
$var wire 16 ," output1 [15:0] $end
$upscope $end
$scope module mux2 $end
$var wire 16 -" input1 [15:0] $end
$var wire 16 ." input2 [15:0] $end
$var wire 1 /" selector $end
$var wire 16 0" output1 [15:0] $end
$upscope $end
$upscope $end
$scope module mux2 $end
$var wire 16 1" input1 [15:0] $end
$var wire 16 2" input2 [15:0] $end
$var wire 16 3" input3 [15:0] $end
$var wire 16 4" input4 [15:0] $end
$var wire 2 5" selector [1:0] $end
$var wire 16 6" submodule2 [15:0] $end
$var wire 16 7" submodule1 [15:0] $end
$var wire 16 8" output1 [15:0] $end
$scope module mux1 $end
$var wire 16 9" input1 [15:0] $end
$var wire 16 :" input2 [15:0] $end
$var wire 1 ;" selector $end
$var wire 16 <" output1 [15:0] $end
$upscope $end
$scope module mux2 $end
$var wire 16 =" input1 [15:0] $end
$var wire 16 >" input2 [15:0] $end
$var wire 1 ?" selector $end
$var wire 16 @" output1 [15:0] $end
$upscope $end
$upscope $end
$upscope $end
$upscope $end
$upscope $end
$enddefinitions $end
#0
$dumpvars
b1110100111111001 @"
0?"
b10010011000110 >"
b1110100111111001 ="
b101011111101101 <"
0;"
b1111011110001100 :"
b101011111101101 9"
b101011111101101 8"
b101011111101101 7"
b1110100111111001 6"
b0 5"
b10010011000110 4"
b1110100111111001 3"
b1111011110001100 2"
b101011111101101 1"
b1111000101110110 0"
0/"
b1100110100111101 ."
b1111000101110110 -"
b1110001100000001 ,"
0+"
b1100110100001101 *"
b1110001100000001 )"
b1110001100000001 ("
b1110001100000001 '"
b1111000101110110 &"
b0 %"
b1100110100111101 $"
b1111000101110110 #"
b1100110100001101 ""
b1110001100000001 !"
b1110001100000001 ~
b1110001100000001 }
b101011111101101 |
b0 {
b10010011000110 z
b1110100111111001 y
b1111011110001100 x
b101011111101101 w
b1100110100111101 v
b1111000101110110 u
b1100110100001101 t
b1110001100000001 s
b1000010001100101 r
0q
b101001000010010 p
b1000010001100101 o
b111101100001101 n
0m
b1001100110001101 l
b111101100001101 k
b111101100001101 j
b111101100001101 i
b1000010001100101 h
b0 g
b101001000010010 f
b1000010001100101 e
b1001100110001101 d
b111101100001101 c
b1101011000001001 b
0a
b101011001100011 `
b1101011000001001 _
b11010100100100 ^
0]
b101111010000001 \
b11010100100100 [
b11010100100100 Z
b11010100100100 Y
b1101011000001001 X
b0 W
b101011001100011 V
b1101011000001001 U
b101111010000001 T
b11010100100100 S
b11010100100100 R
b11010100100100 Q
b111101100001101 P
b0 O
b101001000010010 N
b1000010001100101 M
b1001100110001101 L
b111101100001101 K
b101011001100011 J
b1101011000001001 I
b101111010000001 H
b11010100100100 G
b11010100100100 F
b11010100100100 E
b1110001100000001 D
b0 C
b1110001100000001 B
b101001000010010 A
b1000010001100101 @
b1001100110001101 ?
b111101100001101 >
b101011001100011 =
b1101011000001001 <
b101111010000001 ;
b10010011000110 :
b1110100111111001 9
b1111011110001100 8
b101011111101101 7
b1100110100111101 6
b1111000101110110 5
b1100110100001101 4
b11010100100100 3
b0 2
b1110001100000001 1
b101001000010010 0
b1000010001100101 /
b1001100110001101 .
b111101100001101 -
b101011001100011 ,
b1101011000001001 +
b101111010000001 *
b10010011000110 )
b1110100111111001 (
b1111011110001100 '
b101011111101101 &
b1100110100111101 %
b1111000101110110 $
b1100110100001101 #
b11010100100100 "
b11010100100100 !
$end
#1
b101111010000001 !
b101111010000001 F
b101111010000001 E
b101111010000001 R
b1100110100001101 D
b1100110100001101 ~
b101111010000001 Q
b101111010000001 Z
b1001100110001101 P
b1001100110001101 j
b1100110100001101 }
b1100110100001101 ("
b1111011110001100 |
b1111011110001100 8"
b101111010000001 Y
b101111010000001 ^
b101011001100011 X
b101011001100011 b
b1001100110001101 i
b1001100110001101 n
b101001000010010 h
b101001000010010 r
b1100110100001101 '"
b1100110100001101 ,"
b1100110100111101 &"
b1100110100111101 0"
b1111011110001100 7"
b1111011110001100 <"
b10010011000110 6"
b10010011000110 @"
1]
1a
1m
1q
1+"
1/"
1;"
1?"
b1 W
b1 g
b1 %"
b1 5"
b1 O
b1 {
b1 2
b1 C
#2
b1101011000001001 !
b1101011000001001 F
b1101011000001001 E
b1101011000001001 R
b1111000101110110 D
b1111000101110110 ~
b11010100100100 Y
b11010100100100 ^
b1101011000001001 X
b1101011000001001 b
b1101011000001001 Q
b1101011000001001 Z
b111101100001101 i
b111101100001101 n
b1000010001100101 h
b1000010001100101 r
b1000010001100101 P
b1000010001100101 j
b1110001100000001 '"
b1110001100000001 ,"
b1111000101110110 &"
b1111000101110110 0"
b1111000101110110 }
b1111000101110110 ("
b101011111101101 7"
b101011111101101 <"
b1110100111111001 6"
b1110100111111001 @"
b1110100111111001 |
b1110100111111001 8"
0]
0a
0m
0q
0+"
0/"
0;"
0?"
b10 W
b10 g
b10 %"
b10 5"
b10 O
b10 {
b10 2
b10 C
#3
b101011001100011 !
b101011001100011 F
b101011001100011 E
b101011001100011 R
b1100110100111101 D
b1100110100111101 ~
b101011001100011 Q
b101011001100011 Z
b101001000010010 P
b101001000010010 j
b1100110100111101 }
b1100110100111101 ("
b10010011000110 |
b10010011000110 8"
b101111010000001 Y
b101111010000001 ^
b101011001100011 X
b101011001100011 b
b1001100110001101 i
b1001100110001101 n
b101001000010010 h
b101001000010010 r
b1100110100001101 '"
b1100110100001101 ,"
b1100110100111101 &"
b1100110100111101 0"
b1111011110001100 7"
b1111011110001100 <"
b10010011000110 6"
b10010011000110 @"
1]
1a
1m
1q
1+"
1/"
1;"
1?"
b11 W
b11 g
b11 %"
b11 5"
b11 O
b11 {
b11 2
b11 C
#4
b11010100100100 Y
b11010100100100 ^
b1101011000001001 X
b1101011000001001 b
b11010100100100 Q
b11010100100100 Z
b111101100001101 i
b111101100001101 n
b1000010001100101 h
b1000010001100101 r
b111101100001101 P
b111101100001101 j
b111101100001101 !
b111101100001101 F
b1110001100000001 '"
b1110001100000001 ,"
b1111000101110110 &"
b1111000101110110 0"
b1110001100000001 }
b1110001100000001 ("
b101011111101101 7"
b101011111101101 <"
b1110100111111001 6"
b1110100111111001 @"
b101011111101101 |
b101011111101101 8"
0]
0a
0m
0q
b111101100001101 E
b111101100001101 R
0+"
0/"
0;"
0?"
b101011111101101 D
b101011111101101 ~
b0 W
b0 g
b0 %"
b0 5"
b100 O
b100 {
b100 2
b100 C
#5
b1001100110001101 !
b1001100110001101 F
b1001100110001101 E
b1001100110001101 R
b1111011110001100 D
b1111011110001100 ~
b101111010000001 Q
b101111010000001 Z
b1001100110001101 P
b1001100110001101 j
b1100110100001101 }
b1100110100001101 ("
b1111011110001100 |
b1111011110001100 8"
b101111010000001 Y
b101111010000001 ^
b101011001100011 X
b101011001100011 b
b1001100110001101 i
b1001100110001101 n
b101001000010010 h
b101001000010010 r
b1100110100001101 '"
b1100110100001101 ,"
b1100110100111101 &"
b1100110100111101 0"
b1111011110001100 7"
b1111011110001100 <"
b10010011000110 6"
b10010011000110 @"
1]
1a
1m
1q
1+"
1/"
1;"
1?"
b1 W
b1 g
b1 %"
b1 5"
b101 O
b101 {
b101 2
b101 C
#6
b1000010001100101 !
b1000010001100101 F
b1000010001100101 E
b1000010001100101 R
b1110100111111001 D
b1110100111111001 ~
b11010100100100 Y
b11010100100100 ^
b1101011000001001 X
b1101011000001001 b
b1101011000001001 Q
b1101011000001001 Z
b111101100001101 i
b111101100001101 n
b1000010001100101 h
b1000010001100101 r
b1000010001100101 P
b1000010001100101 j
b1110001100000001 '"
b1110001100000001 ,"
b1111000101110110 &"
b1111000101110110 0"
b1111000101110110 }
b1111000101110110 ("
b101011111101101 7"
b101011111101101 <"
b1110100111111001 6"
b1110100111111001 @"
b1110100111111001 |
b1110100111111001 8"
0]
0a
0m
0q
0+"
0/"
0;"
0?"
b10 W
b10 g
b10 %"
b10 5"
b110 O
b110 {
b110 2
b110 C
#7
b101001000010010 !
b101001000010010 F
b101001000010010 E
b101001000010010 R
b10010011000110 D
b10010011000110 ~
b101011001100011 Q
b101011001100011 Z
b101001000010010 P
b101001000010010 j
b1100110100111101 }
b1100110100111101 ("
b10010011000110 |
b10010011000110 8"
b101111010000001 Y
b101111010000001 ^
b101011001100011 X
b101011001100011 b
b1001100110001101 i
b1001100110001101 n
b101001000010010 h
b101001000010010 r
b1100110100001101 '"
b1100110100001101 ,"
b1100110100111101 &"
b1100110100111101 0"
b1111011110001100 7"
b1111011110001100 <"
b10010011000110 6"
b10010011000110 @"
1]
1a
1m
1q
1+"
1/"
1;"
1?"
b11 W
b11 g
b11 %"
b11 5"
b111 O
b111 {
b111 2
b111 C
#8
b11010100100100 Y
b11010100100100 ^
b1101011000001001 X
b1101011000001001 b
b11010100100100 Q
b11010100100100 Z
b111101100001101 i
b111101100001101 n
b1000010001100101 h
b1000010001100101 r
b111101100001101 P
b111101100001101 j
b1110001100000001 '"
b1110001100000001 ,"
b1111000101110110 &"
b1111000101110110 0"
b1110001100000001 }
b1110001100000001 ("
b101011111101101 7"
b101011111101101 <"
b1110100111111001 6"
b1110100111111001 @"
b101011111101101 |
b101011111101101 8"
0]
0a
0m
0q
b11010100100100 E
b11010100100100 R
0+"
0/"
0;"
0?"
b1110001100000001 D
b1110001100000001 ~
b0 W
b0 g
b0 %"
b0 5"
b1110001100000001 !
b1110001100000001 F
b0 O
b0 {
b1000 2
b1000 C
#9
b1100110100001101 !
b1100110100001101 F
b101111010000001 E
b101111010000001 R
b1100110100001101 D
b1100110100001101 ~
b101111010000001 Q
b101111010000001 Z
b1001100110001101 P
b1001100110001101 j
b1100110100001101 }
b1100110100001101 ("
b1111011110001100 |
b1111011110001100 8"
b101111010000001 Y
b101111010000001 ^
b101011001100011 X
b101011001100011 b
b1001100110001101 i
b1001100110001101 n
b101001000010010 h
b101001000010010 r
b1100110100001101 '"
b1100110100001101 ,"
b1100110100111101 &"
b1100110100111101 0"
b1111011110001100 7"
b1111011110001100 <"
b10010011000110 6"
b10010011000110 @"
1]
1a
1m
1q
1+"
1/"
1;"
1?"
b1 W
b1 g
b1 %"
b1 5"
b1 O
b1 {
b1001 2
b1001 C
#10
b1111000101110110 !
b1111000101110110 F
b1101011000001001 E
b1101011000001001 R
b1111000101110110 D
b1111000101110110 ~
b11010100100100 Y
b11010100100100 ^
b1101011000001001 X
b1101011000001001 b
b1101011000001001 Q
b1101011000001001 Z
b111101100001101 i
b111101100001101 n
b1000010001100101 h
b1000010001100101 r
b1000010001100101 P
b1000010001100101 j
b1110001100000001 '"
b1110001100000001 ,"
b1111000101110110 &"
b1111000101110110 0"
b1111000101110110 }
b1111000101110110 ("
b101011111101101 7"
b101011111101101 <"
b1110100111111001 6"
b1110100111111001 @"
b1110100111111001 |
b1110100111111001 8"
0]
0a
0m
0q
0+"
0/"
0;"
0?"
b10 W
b10 g
b10 %"
b10 5"
b10 O
b10 {
b1010 2
b1010 C
#11
b1100110100111101 !
b1100110100111101 F
b101011001100011 E
b101011001100011 R
b1100110100111101 D
b1100110100111101 ~
b101011001100011 Q
b101011001100011 Z
b101001000010010 P
b101001000010010 j
b1100110100111101 }
b1100110100111101 ("
b10010011000110 |
b10010011000110 8"
b101111010000001 Y
b101111010000001 ^
b101011001100011 X
b101011001100011 b
b1001100110001101 i
b1001100110001101 n
b101001000010010 h
b101001000010010 r
b1100110100001101 '"
b1100110100001101 ,"
b1100110100111101 &"
b1100110100111101 0"
b1111011110001100 7"
b1111011110001100 <"
b10010011000110 6"
b10010011000110 @"
1]
1a
1m
1q
1+"
1/"
1;"
1?"
b11 W
b11 g
b11 %"
b11 5"
b11 O
b11 {
b1011 2
b1011 C
#12
b11010100100100 Y
b11010100100100 ^
b1101011000001001 X
b1101011000001001 b
b11010100100100 Q
b11010100100100 Z
b111101100001101 i
b111101100001101 n
b1000010001100101 h
b1000010001100101 r
b111101100001101 P
b111101100001101 j
b1110001100000001 '"
b1110001100000001 ,"
b1111000101110110 &"
b1111000101110110 0"
b1110001100000001 }
b1110001100000001 ("
b101011111101101 7"
b101011111101101 <"
b1110100111111001 6"
b1110100111111001 @"
b101011111101101 |
b101011111101101 8"
b101011111101101 !
b101011111101101 F
0]
0a
0m
0q
b111101100001101 E
b111101100001101 R
0+"
0/"
0;"
0?"
b101011111101101 D
b101011111101101 ~
b0 W
b0 g
b0 %"
b0 5"
b100 O
b100 {
b1100 2
b1100 C
#13
b1111011110001100 !
b1111011110001100 F
b1001100110001101 E
b1001100110001101 R
b1111011110001100 D
b1111011110001100 ~
b101111010000001 Q
b101111010000001 Z
b1001100110001101 P
b1001100110001101 j
b1100110100001101 }
b1100110100001101 ("
b1111011110001100 |
b1111011110001100 8"
b101111010000001 Y
b101111010000001 ^
b101011001100011 X
b101011001100011 b
b1001100110001101 i
b1001100110001101 n
b101001000010010 h
b101001000010010 r
b1100110100001101 '"
b1100110100001101 ,"
b1100110100111101 &"
b1100110100111101 0"
b1111011110001100 7"
b1111011110001100 <"
b10010011000110 6"
b10010011000110 @"
1]
1a
1m
1q
1+"
1/"
1;"
1?"
b1 W
b1 g
b1 %"
b1 5"
b101 O
b101 {
b1101 2
b1101 C
#14
b1110100111111001 !
b1110100111111001 F
b1000010001100101 E
b1000010001100101 R
b1110100111111001 D
b1110100111111001 ~
b11010100100100 Y
b11010100100100 ^
b1101011000001001 X
b1101011000001001 b
b1101011000001001 Q
b1101011000001001 Z
b111101100001101 i
b111101100001101 n
b1000010001100101 h
b1000010001100101 r
b1000010001100101 P
b1000010001100101 j
b1110001100000001 '"
b1110001100000001 ,"
b1111000101110110 &"
b1111000101110110 0"
b1111000101110110 }
b1111000101110110 ("
b101011111101101 7"
b101011111101101 <"
b1110100111111001 6"
b1110100111111001 @"
b1110100111111001 |
b1110100111111001 8"
0]
0a
0m
0q
0+"
0/"
0;"
0?"
b10 W
b10 g
b10 %"
b10 5"
b110 O
b110 {
b1110 2
b1110 C
#15
b10010011000110 !
b10010011000110 F
b101001000010010 E
b101001000010010 R
b10010011000110 D
b10010011000110 ~
b101011001100011 Q
b101011001100011 Z
b101001000010010 P
b101001000010010 j
b1100110100111101 }
b1100110100111101 ("
b10010011000110 |
b10010011000110 8"
b101111010000001 Y
b101111010000001 ^
b101011001100011 X
b101011001100011 b
b1001100110001101 i
b1001100110001101 n
b101001000010010 h
b101001000010010 r
b1100110100001101 '"
b1100110100001101 ,"
b1100110100111101 &"
b1100110100111101 0"
b1111011110001100 7"
b1111011110001100 <"
b10010011000110 6"
b10010011000110 @"
1]
1a
1m
1q
1+"
1/"
1;"
1?"
b11 W
b11 g
b11 %"
b11 5"
b111 O
b111 {
b1111 2
b1111 C
#16
b11010100100100 Y
b11010100100100 ^
b1101011000001001 X
b1101011000001001 b
b11010100100100 Q
b11010100100100 Z
b111101100001101 i
b111101100001101 n
b1000010001100101 h
b1000010001100101 r
b111101100001101 P
b111101100001101 j
b1110001100000001 '"
b1110001100000001 ,"
b1111000101110110 &"
b1111000101110110 0"
b1110001100000001 }
b1110001100000001 ("
b101011111101101 7"
b101011111101101 <"
b1110100111111001 6"
b1110100111111001 @"
b101011111101101 |
b101011111101101 8"
0]
0a
0m
0q
b11010100100100 E
b11010100100100 R
0+"
0/"
0;"
0?"
b1110001100000001 D
b1110001100000001 ~
b0 W
b0 g
b0 %"
b0 5"
b11010100100100 !
b11010100100100 F
b0 O
b0 {
b0 2
b0 C
